Workbook

Sheet README
A1: Fee Switch-Off Calculations
A2: What this is | B2: The numbers behind the S&I SWITCHING OFF FEES SOP, on the same synthetic policies the BaNCS demo uses, so a person (or Seek) can check what BaNCS should show at each step.
A4: Fee Switch-Off | B4: Per policy: the VAT Inclusive Asset Advice Fee now, its VAT Exclusive value, the rand a year it costs the client, and the saving once the fee is set to 0.
A5: Process Checks | B5: Per policy: the SOP's decisions in order. ID check against the work list, error 56000, skip if the fee is already 0.000, and the Legal Verification and acceptance-date actions.
A6: Split Fee | B6: The split commission SOP: the new VAT Inclusive fee when the staying adviser keeps a given share, for example 0.575 at 50% gives 0.287 and 0.250 exclusive, as in the SOP.
A7: Latency Budget | B7: Time spent waiting in one full case on the Normal and Stress profiles, and a suggested timeout per step for Seek.
A8: Quote Summary | B8: What Calculate Premium shows on Endr Quote Summary: the refund (or collection) of the fee for the days left in the fee period, the adviser commission and its clawback. Fee period = previous to next due date; only that period is adjusted.
A9: EAC | B9: The Effective Annual Cost at the four milestones (years 1, 5, 10 and the term; 1, 3, 5 and the term for a 10-year policy), by Investment, Advice, Admin and Other. Excel FV and RATE on monthly contributions, with and without charges.
A11: How to read it | B11: Blue figures are inputs (from BaNCS or the work list); yellow cells can be changed to try other values; black figures are formulas. Nothing on a sheet is typed over a formula.
A12: VAT | B12: VAT Exclusive = VAT Inclusive / 1.15, rounded to 3 decimals, exactly as BaNCS derives it after Save. VAT is set on the Assumptions sheet.
A13: Rounding | B13: Rand amounts round to 2 decimals and fees to 3, half up. Each ROUND carries a +1E-9 guard so binary noise cannot flip an exact half (84,450 x 1.15% is exactly 971.175 and must show 971.18).
A14: Fee units | B14: The fee is a percentage a year of the market value (0.575 means 0.575%). ASSUMPTION: confirm with Old Mutual that the asset advice fee is charged as a yearly percentage of market value; if it is not, only the rand columns change.
A15: Split rule | B15: New VAT Inclusive fee = current fee x the staying adviser's asset advice fee share, rounded DOWN to 3 decimals. This is the build's reading of the SOP's "adjust the fee for the remaining adviser to receive the same fees"; it reproduces the SOP's 0.575 to 0.287.
... A17: Synthetic data | B17: Every client, ID number and amount is fictional.

Sheet Assumptions
A1: Assumptions
A3: VAT factor (1 + 15%) | B3: 1.15 | C3: South African VAT at 15%. BaNCS shows VAT Exclusive = VAT Inclusive / this.
A4: Months in a year | B4: 12 | C4: Used for the monthly fee.
A5: System date | B5: 04/08/2026 | C5: The BaNCS system date; an approved quote effective after it blocks a new endorsement (error 56000).
A6: Endorsement effective date | B6: 46238 | C6: The date the fee change takes effect on the quote (the BaNCS system date unless a later date is chosen). Drives the refund.
A7: Fund charge, LISP (% a year) | B7: 0.85 | C7: ASSUMPTION: fund total expense ratio for OMS LISP Investment. Confirm with Old Mutual.
A8: Fund charge, TFI II (% a year) | B8: 0.7 | C8: ASSUMPTION: fund total expense ratio for OMS TFI II. Confirm with Old Mutual.
A9: Platform admin charge (% a year) | B9: 0.35 | C9: ASSUMPTION: matches the 0.35 used for the net yield in the data.
A10: Initial charge (% of each contribution) | B10: 1.725 | C10: From the data: R10.35 off R600.00 (policy A) is 1.725%.
A11: Other charges (% a year) | B11: 0 | C11: Nothing else is charged on these products.

Sheet Fee Switch-Off
A1: Fee Switch-Off: what the client pays now and after the fee is set to 0
A2: Blue = from BaNCS. Yellow = change to try another new fee. The saving only counts policies the process will actually change (see Process Checks).
A4: Contract No. | B4: Client | C4: Product | D4: Scenario | E4: Market value (R) | F4: Monthly contribution (R) | G4: VAT Inclusive fee now (%) | H4: VAT Exclusive fee now (%) | I4: Fee a year now (R) | J4: Fee a month now (R) | K4: New VAT Inclusive fee (%) | L4: New VAT Exclusive fee (%) | M4: Fee a year after (R) | N4: Saving a year (R) | O4: Will the process change it?
A5: 119900001001 | B5: NOKUTHULA MAHLOBO | C5: OMS LISP Investment | D5: happy | E5: 4323.48 | F5: 600 | G5: 0.575 | H5: =ROUND(G5/Assumptions!$B$3+1E-9,3) -> 0.5 | I5: =ROUND(E5*G5/100+1E-9,2) -> 24.86 | J5: =ROUND(I5/Assumptions!$B$4+1E-9,2) -> 2.07 | K5: 0 | L5: =ROUND(K5/Assumptions!$B$3+1E-9,3) -> 0 | M5: =ROUND(E5*K5/100+1E-9,2) -> 0 | N5: =I5-M5 -> 24.86 | O5: =IF(LEFT(INDEX('Process Checks'!$K$5:$K$30,MATCH($A5,'Process Checks'!$A$5:$A$30,0)),7)="PROCEED","Yes","No") -> Yes
A6: 110671307001 | B6: SIPHO KHUMALO | C6: OMS TFI II | D6: happy | E6: 84450 | F6: 2500 | G6: 1.15 | H6: =ROUND(G6/Assumptions!$B$3+1E-9,3) -> 1 | I6: =ROUND(E6*G6/100+1E-9,2) -> 971.18 | J6: =ROUND(I6/Assumptions!$B$4+1E-9,2) -> 80.93 | K6: 0 | L6: =ROUND(K6/Assumptions!$B$3+1E-9,3) -> 0 | M6: =ROUND(E6*K6/100+1E-9,2) -> 0 | N6: =I6-M6 -> 971.18 | O6: =IF(LEFT(INDEX('Process Checks'!$K$5:$K$30,MATCH($A6,'Process Checks'!$A$5:$A$30,0)),7)="PROCEED","Yes","No") -> Yes
A7: 112333103001 | B7: THANDEKA ZULU | C7: OMS LISP Investment | D7: happy | E7: 36074.16 | F7: 1200 | G7: 0.863 | H7: =ROUND(G7/Assumptions!$B$3+1E-9,3) -> 0.75 | I7: =ROUND(E7*G7/100+1E-9,2) -> 311.32 | J7: =ROUND(I7/Assumptions!$B$4+1E-9,2) -> 25.94 | K7: 0 | L7: =ROUND(K7/Assumptions!$B$3+1E-9,3) -> 0 | M7: =ROUND(E7*K7/100+1E-9,2) -> 0 | N7: =I7-M7 -> 311.32 | O7: =IF(LEFT(INDEX('Process Checks'!$K$5:$K$30,MATCH($A7,'Process Checks'!$A$5:$A$30,0)),7)="PROCEED","Yes","No") -> Yes
A8: 112953094001 | B8: RIAAN STEYN | C8: OMS TFI II | D8: happy | E8: 75665.4 | F8: 3000 | G8: 0.575 | H8: =ROUND(G8/Assumptions!$B$3+1E-9,3) -> 0.5 | I8: =ROUND(E8*G8/100+1E-9,2) -> 435.08 | J8: =ROUND(I8/Assumptions!$B$4+1E-9,2) -> 36.26 | K8: 0 | L8: =ROUND(K8/Assumptions!$B$3+1E-9,3) -> 0 | M8: =ROUND(E8*K8/100+1E-9,2) -> 0 | N8: =I8-M8 -> 435.08 | O8: =IF(LEFT(INDEX('Process Checks'!$K$5:$K$30,MATCH($A8,'Process Checks'!$A$5:$A$30,0)),7)="PROCEED","Yes","No") -> Yes
A9: 113162231001 | B9: AYESHA PATEL | C9: OMS LISP Investment | D9: happy | E9: 92322.9 | F9: 4500 | G9: 1.438 | H9: =ROUND(G9/Assumptions!$B$3+1E-9,3) -> 1.25 | I9: =ROUND(E9*G9/100+1E-9,2) -> 1327.6 | J9: =ROUND(I9/Assumptions!$B$4+1E-9,2) -> 110.63 | K9: 0 | L9: =ROUND(K9/Assumptions!$B$3+1E-9,3) -> 0 | M9: =ROUND(E9*K9/100+1E-9,2) -> 0 | N9: =I9-M9 -> 1327.6 | O9: =IF(LEFT(INDEX('Process Checks'!$K$5:$K$30,MATCH($A9,'Process Checks'!$A$5:$A$30,0)),7)="PROCEED","Yes","No") -> Yes
A10: 113165622001 | B10: KAGISO MOLEFE | C10: OMS LISP Investment | D10: happy | E10: 30774.3 | F10: 1500 | G10: 1.15 | H10: =ROUND(G10/Assumptions!$B$3+1E-9,3) -> 1 | I10: =ROUND(E10*G10/100+1E-9,2) -> 353.9 | J10: =ROUND(I10/Assumptions!$B$4+1E-9,2) -> 29.49 | K10: 0 | L10: =ROUND(K10/Assumptions!$B$3+1E-9,3) -> 0 | M10: =ROUND(E10*K10/100+1E-9,2) -> 0 | N10: =I10-M10 -> 353.9 | O10: =IF(LEFT(INDEX('Process Checks'!$K$5:$K$30,MATCH($A10,'Process Checks'!$A$5:$A$30,0)),7)="PROCEED","Yes","No") -> Yes
A11: 113402518001 | B11: CHARLENE ADAMS | C11: OMS TFI II | D11: happy | E11: 18213.8 | F11: 1000 | G11: 0.69 | H11: =ROUND(G11/Assumptions!$B$3+1E-9,3) -> 0.6 | I11: =ROUND(E11*G11/100+1E-9,2) -> 125.68 | J11: =ROUND(I11/Assumptions!$B$4+1E-9,2) -> 10.47 | K11: 0 | L11: =ROUND(K11/Assumptions!$B$3+1E-9,3) -> 0 | M11: =ROUND(E11*K11/100+1E-9,2) -> 0 | N11: =I11-M11 -> 125.68 | O11: =IF(LEFT(INDEX('Process Checks'!$K$5:$K$30,MATCH($A11,'Process Checks'!$A$5:$A$30,0)),7)="PROCEED","Yes","No") -> Yes
A12: 113577840001 | B12: BONGANI MAHLANGU | C12: OMS LISP Investment | D12: happy | E12: 29646.4 | F12: 2000 | G12: 1.035 | H12: =ROUND(G12/Assumptions!$B$3+1E-9,3) -> 0.9 | I12: =ROUND(E12*G12/100+1E-9,2) -> 306.84 | J12: =ROUND(I12/Assumptions!$B$4+1E-9,2) -> 25.57 | K12: 0 | L12: =ROUND(K12/Assumptions!$B$3+1E-9,3) -> 0 | M12: =ROUND(E12*K12/100+1E-9,2) -> 0 | N12: =I12-M12 -> 306.84 | O12: =IF(LEFT(INDEX('Process Checks'!$K$5:$K$30,MATCH($A12,'Process Checks'!$A$5:$A$30,0)),7)="PROCEED","Yes","No") -> Yes
A13: 111890254001 | B13: FATIMA OSMAN | C13: OMS LISP Investment | D13: happy | E13: 149814 | F13: 2800 | G13: 0.46 | H13: =ROUND(G13/Assumptions!$B$3+1E-9,3) -> 0.4 | I13: =ROUND(E13*G13/100+1E-9,2) -> 689.14 | J13: =ROUND(I13/Assumptions!$B$4+1E-9,2) -> 57.43 | K13: 0 | L13: =ROUND(K13/Assumptions!$B$3+1E-9,3) -> 0 | M13: =ROUND(E13*K13/100+1E-9,2) -> 0 | N13: =I13-M13 -> 689.14 | O13: =IF(LEFT(INDEX('Process Checks'!$K$5:$K$30,MATCH($A13,'Process Checks'!$A$5:$A$30,0)),7)="PROCEED","Yes","No") -> Yes
A14: 112045877001 | B14: ITUMELENG SELLO | C14: OMS TFI II | D14: happy | E14: 88935.84 | F14: 1800 | G14: 0.92 | H14: =ROUND(G14/Assumptions!$B$3+1E-9,3) -> 0.8 | I14: =ROUND(E14*G14/100+1E-9,2) -> 818.21 | J14: =ROUND(I14/Assumptions!$B$4+1E-9,2) -> 68.18 | K14: 0 | L14: =ROUND(K14/Assumptions!$B$3+1E-9,3) -> 0 | M14: =ROUND(E14*K14/100+1E-9,2) -> 0 | N14: =I14-M14 -> 818.21 | O14: =IF(LEFT(INDEX('Process Checks'!$K$5:$K$30,MATCH($A14,'Process Checks'!$A$5:$A$30,0)),7)="PROCEED","Yes","No") -> Yes
A15: 112476310001 | B15: CHANTEL VAN WYK | C15: OMS LISP Investment | D15: happy | E15: 140507.5 | F15: 3500 | G15: 1.725 | H15: =ROUND(G15/Assumptions!$B$3+1E-9,3) -> 1.5 | I15: =ROUND(E15*G15/100+1E-9,2) -> 2423.75 | J15: =ROUND(I15/Assumptions!$B$4+1E-9,2) -> 201.98 | K15: 0 | L15: =ROUND(K15/Assumptions!$B$3+1E-9,3) -> 0 | M15: =ROUND(E15*K15/100+1E-9,2) -> 0 | N15: =I15-M15 -> 2423.75 | O15: =IF(LEFT(INDEX('Process Checks'!$K$5:$K$30,MATCH($A15,'Process Checks'!$A$5:$A$30,0)),7)="PROCEED","Yes","No") -> Yes
A16: 112718459001 | B16: MPHO DLAMINI | C16: OMS TFI II | D16: happy | E16: 21021.72 | F16: 600 | G16: 0.345 | H16: =ROUND(G16/Assumptions!$B$3+1E-9,3) -> 0.3 | I16: =ROUND(E16*G16/100+1E-9,2) -> 72.52 | J16: =ROUND(I16/Assumptions!$B$4+1E-9,2) -> 6.04 | K16: 0 | L16: =ROUND(K16/Assumptions!$B$3+1E-9,3) -> 0 | M16: =ROUND(E16*K16/100+1E-9,2) -> 0 | N16: =I16-M16 -> 72.52 | O16: =IF(LEFT(INDEX('Process Checks'!$K$5:$K$30,MATCH($A16,'Process Checks'!$A$5:$A$30,0)),7)="PROCEED","Yes","No") -> Yes
... A30: 114723506001 | B30: RUBEN PILLAY | C30: OMS LISP Investment | D30: split | E30: 17293.92 | F30: 2400 | G30: 1.15 | H30: =ROUND(G30/Assumptions!$B$3+1E-9,3) -> 1 | I30: =ROUND(E30*G30/100+1E-9,2) -> 198.88 | J30: =ROUND(I30/Assumptions!$B$4+1E-9,2) -> 16.57 | K30: 0 | L30: =ROUND(K30/Assumptions!$B$3+1E-9,3) -> 0 | M30: =ROUND(E30*K30/100+1E-9,2) -> 0 | N30: =I30-M30 -> 198.88 | O30: =IF(LEFT(INDEX('Process Checks'!$K$5:$K$30,MATCH($A30,'Process Checks'!$A$5:$A$30,0)),7)="PROCEED","Yes","No") -> Yes
A32: Total for the policies the process changes | I32: =SUMIF($O$5:$O$30,"Yes",I5:I30) -> 10459.89 | M32: =SUMIF($O$5:$O$30,"Yes",M5:M30) -> 0 | N32: =SUMIF($O$5:$O$30,"Yes",N5:N30) -> 10459.89 | O32: =COUNTIF($O$5:$O$30,"Yes")&" policies" -> 20 policies

Sheet Process Checks
A1: Process Checks: the SOP's decisions, in order
A2: Order of the checks: (1) ID number against the work list, (2) Endorse/Alter allowed? (error 56000), (3) skip if the fee is already 0.000. Compare Expected outcome with what Seek does.
A4: Contract No. | B4: Client | C4: ID number in BaNCS | D4: ID number on the work list | E4: ID check | F4: Endorsement already in progress? | G4: What is in progress | H4: VAT Inclusive fee now (%) | I4: Legal Verification default | J4: Declaration signed (work list) | K4: Expected outcome | L4: Status path if processed | M4: Legal Verification action | N4: Acceptance date to enter
A5: 119900001001 | B5: NOKUTHULA MAHLOBO | C5: 8609144417086 | D5: 8609144417086 | E5: =IF(C5=D5,"MATCH","MISMATCH") -> MATCH | F5: No | H5: =INDEX('Fee Switch-Off'!$G$5:$G$30,MATCH($A5,'Fee Switch-Off'!$A$5:$A$30,0)) -> 0.575 | I5: Approved | J5: 04/08/2026 | K5: =IF(E5="MISMATCH","STOP: ID number does not match the work list",IF(F5="Yes","STOP: error 56000, an endorsement is already in progress",IF(H5=0,"SKIP: fee already 0.000","PROCEED: set VAT Inclusive fee to 0"))) -> PROCEED: set VAT Inclusive fee to 0 | L5: =IF(LEFT(K5,7)="PROCEED","ACTIVE POLICY > DRAFT ENDORSEMENT QUOTE > FINAL ENDORSEMENT QUOTE (Submitted) > Approved Endorsed Quote","No endorsement is raised") -> ACTIVE POLICY > DRAFT ENDORSEMENT QUOTE > FINAL ENDORSEMENT QUOTE (Submitted) > Approved Endorsed Quote | M5: =IF(LEFT(K5,7)<>"PROCEED","n/a",IF(I5="(blank)","Select Approved before Submit","Already Approved")) -> Already Approved | N5: =IF(LEFT(K5,7)="PROCEED",J5,"n/a") -> 04/08/2026
A6: 110671307001 | B6: SIPHO KHUMALO | C6: 7903149806083 | D6: 7903149806083 | E6: =IF(C6=D6,"MATCH","MISMATCH") -> MATCH | F6: No | H6: =INDEX('Fee Switch-Off'!$G$5:$G$30,MATCH($A6,'Fee Switch-Off'!$A$5:$A$30,0)) -> 1.15 | I6: Approved | J6: 01/08/2026 | K6: =IF(E6="MISMATCH","STOP: ID number does not match the work list",IF(F6="Yes","STOP: error 56000, an endorsement is already in progress",IF(H6=0,"SKIP: fee already 0.000","PROCEED: set VAT Inclusive fee to 0"))) -> PROCEED: set VAT Inclusive fee to 0 | L6: =IF(LEFT(K6,7)="PROCEED","ACTIVE POLICY > DRAFT ENDORSEMENT QUOTE > FINAL ENDORSEMENT QUOTE (Submitted) > Approved Endorsed Quote","No endorsement is raised") -> ACTIVE POLICY > DRAFT ENDORSEMENT QUOTE > FINAL ENDORSEMENT QUOTE (Submitted) > Approved Endorsed Quote | M6: =IF(LEFT(K6,7)<>"PROCEED","n/a",IF(I6="(blank)","Select Approved before Submit","Already Approved")) -> Already Approved | N6: =IF(LEFT(K6,7)="PROCEED",J6,"n/a") -> 01/08/2026
A7: 112333103001 | B7: THANDEKA ZULU | C7: 9011220195083 | D7: 9011220195083 | E7: =IF(C7=D7,"MATCH","MISMATCH") -> MATCH | F7: No | H7: =INDEX('Fee Switch-Off'!$G$5:$G$30,MATCH($A7,'Fee Switch-Off'!$A$5:$A$30,0)) -> 0.863 | I7: (blank) | J7: 31/07/2026 | K7: =IF(E7="MISMATCH","STOP: ID number does not match the work list",IF(F7="Yes","STOP: error 56000, an endorsement is already in progress",IF(H7=0,"SKIP: fee already 0.000","PROCEED: set VAT Inclusive fee to 0"))) -> PROCEED: set VAT Inclusive fee to 0 | L7: =IF(LEFT(K7,7)="PROCEED","ACTIVE POLICY > DRAFT ENDORSEMENT QUOTE > FINAL ENDORSEMENT QUOTE (Submitted) > Approved Endorsed Quote","No endorsement is raised") -> ACTIVE POLICY > DRAFT ENDORSEMENT QUOTE > FINAL ENDORSEMENT QUOTE (Submitted) > Approved Endorsed Quote | M7: =IF(LEFT(K7,7)<>"PROCEED","n/a",IF(I7="(blank)","Select Approved before Submit","Already Approved")) -> Select Approved before Submit | N7: =IF(LEFT(K7,7)="PROCEED",J7,"n/a") -> 31/07/2026
A8: 112953094001 | B8: RIAAN STEYN | C8: 7207025584081 | D8: 7207025584081 | E8: =IF(C8=D8,"MATCH","MISMATCH") -> MATCH | F8: No | H8: =INDEX('Fee Switch-Off'!$G$5:$G$30,MATCH($A8,'Fee Switch-Off'!$A$5:$A$30,0)) -> 0.575 | I8: Approved | J8: 03/08/2026 | K8: =IF(E8="MISMATCH","STOP: ID number does not match the work list",IF(F8="Yes","STOP: error 56000, an endorsement is already in progress",IF(H8=0,"SKIP: fee already 0.000","PROCEED: set VAT Inclusive fee to 0"))) -> PROCEED: set VAT Inclusive fee to 0 | L8: =IF(LEFT(K8,7)="PROCEED","ACTIVE POLICY > DRAFT ENDORSEMENT QUOTE > FINAL ENDORSEMENT QUOTE (Submitted) > Approved Endorsed Quote","No endorsement is raised") -> ACTIVE POLICY > DRAFT ENDORSEMENT QUOTE > FINAL ENDORSEMENT QUOTE (Submitted) > Approved Endorsed Quote | M8: =IF(LEFT(K8,7)<>"PROCEED","n/a",IF(I8="(blank)","Select Approved before Submit","Already Approved")) -> Already Approved | N8: =IF(LEFT(K8,7)="PROCEED",J8,"n/a") -> 03/08/2026
A9: 113162231001 | B9: AYESHA PATEL | C9: 8809190973087 | D9: 8809190973087 | E9: =IF(C9=D9,"MATCH","MISMATCH") -> MATCH | F9: No | H9: =INDEX('Fee Switch-Off'!$G$5:$G$30,MATCH($A9,'Fee Switch-Off'!$A$5:$A$30,0)) -> 1.438 | I9: Approved | J9: 30/07/2026 | K9: =IF(E9="MISMATCH","STOP: ID number does not match the work list",IF(F9="Yes","STOP: error 56000, an endorsement is already in progress",IF(H9=0,"SKIP: fee already 0.000","PROCEED: set VAT Inclusive fee to 0"))) -> PROCEED: set VAT Inclusive fee to 0 | L9: =IF(LEFT(K9,7)="PROCEED","ACTIVE POLICY > DRAFT ENDORSEMENT QUOTE > FINAL ENDORSEMENT QUOTE (Submitted) > Approved Endorsed Quote","No endorsement is raised") -> ACTIVE POLICY > DRAFT ENDORSEMENT QUOTE > FINAL ENDORSEMENT QUOTE (Submitted) > Approved Endorsed Quote | M9: =IF(LEFT(K9,7)<>"PROCEED","n/a",IF(I9="(blank)","Select Approved before Submit","Already Approved")) -> Already Approved | N9: =IF(LEFT(K9,7)="PROCEED",J9,"n/a") -> 30/07/2026
A10: 113165622001 | B10: KAGISO MOLEFE | C10: 8305056362085 | D10: 8305056362085 | E10: =IF(C10=D10,"MATCH","MISMATCH") -> MATCH | F10: No | H10: =INDEX('Fee Switch-Off'!$G$5:$G$30,MATCH($A10,'Fee Switch-Off'!$A$5:$A$30,0)) -> 1.15 | I10: Approved | J10: 04/08/2026 | K10: =IF(E10="MISMATCH","STOP: ID number does not match the work list",IF(F10="Yes","STOP: error 56000, an endorsement is already in progress",IF(H10=0,"SKIP: fee already 0.000","PROCEED: set VAT Inclusive fee to 0"))) -> PROCEED: set VAT Inclusive fee to 0 | L10: =IF(LEFT(K10,7)="PROCEED","ACTIVE POLICY > DRAFT ENDORSEMENT QUOTE > FINAL ENDORSEMENT QUOTE (Submitted) > Approved Endorsed Quote","No endorsement is raised") -> ACTIVE POLICY > DRAFT ENDORSEMENT QUOTE > FINAL ENDORSEMENT QUOTE (Submitted) > Approved Endorsed Quote | M10: =IF(LEFT(K10,7)<>"PROCEED","n/a",IF(I10="(blank)","Select Approved before Submit","Already Approved")) -> Already Approved | N10: =IF(LEFT(K10,7)="PROCEED",J10,"n/a") -> 04/08/2026
A11: 113402518001 | B11: CHARLENE ADAMS | C11: 9401271751084 | D11: 9401271751084 | E11: =IF(C11=D11,"MATCH","MISMATCH") -> MATCH | F11: No | H11: =INDEX('Fee Switch-Off'!$G$5:$G$30,MATCH($A11,'Fee Switch-Off'!$A$5:$A$30,0)) -> 0.69 | I11: Approved | J11: 01/08/2026 | K11: =IF(E11="MISMATCH","STOP: ID number does not match the work list",IF(F11="Yes","STOP: error 56000, an endorsement is already in progress",IF(H11=0,"SKIP: fee already 0.000","PROCEED: set VAT Inclusive fee to 0"))) -> PROCEED: set VAT Inclusive fee to 0 | L11: =IF(LEFT(K11,7)="PROCEED","ACTIVE POLICY > DRAFT ENDORSEMENT QUOTE > FINAL ENDORSEMENT QUOTE (Submitted) > Approved Endorsed Quote","No endorsement is raised") -> ACTIVE POLICY > DRAFT ENDORSEMENT QUOTE > FINAL ENDORSEMENT QUOTE (Submitted) > Approved Endorsed Quote | M11: =IF(LEFT(K11,7)<>"PROCEED","n/a",IF(I11="(blank)","Select Approved before Submit","Already Approved")) -> Already Approved | N11: =IF(LEFT(K11,7)="PROCEED",J11,"n/a") -> 01/08/2026
A12: 113577840001 | B12: BONGANI MAHLANGU | C12: 7612117140082 | D12: 7612117140082 | E12: =IF(C12=D12,"MATCH","MISMATCH") -> MATCH | F12: No | H12: =INDEX('Fee Switch-Off'!$G$5:$G$30,MATCH($A12,'Fee Switch-Off'!$A$5:$A$30,0)) -> 1.035 | I12: Approved | J12: 31/07/2026 | K12: =IF(E12="MISMATCH","STOP: ID number does not match the work list",IF(F12="Yes","STOP: error 56000, an endorsement is already in progress",IF(H12=0,"SKIP: fee already 0.000","PROCEED: set VAT Inclusive fee to 0"))) -> PROCEED: set VAT Inclusive fee to 0 | L12: =IF(LEFT(K12,7)="PROCEED","ACTIVE POLICY > DRAFT ENDORSEMENT QUOTE > FINAL ENDORSEMENT QUOTE (Submitted) > Approved Endorsed Quote","No endorsement is raised") -> ACTIVE POLICY > DRAFT ENDORSEMENT QUOTE > FINAL ENDORSEMENT QUOTE (Submitted) > Approved Endorsed Quote | M12: =IF(LEFT(K12,7)<>"PROCEED","n/a",IF(I12="(blank)","Select Approved before Submit","Already Approved")) -> Already Approved | N12: =IF(LEFT(K12,7)="PROCEED",J12,"n/a") -> 31/07/2026
A13: 111890254001 | B13: FATIMA OSMAN | C13: 8108302529089 | D13: 8108302529089 | E13: =IF(C13=D13,"MATCH","MISMATCH") -> MATCH | F13: No | H13: =INDEX('Fee Switch-Off'!$G$5:$G$30,MATCH($A13,'Fee Switch-Off'!$A$5:$A$30,0)) -> 0.46 | I13: Approved | J13: 03/08/2026 | K13: =IF(E13="MISMATCH","STOP: ID number does not match the work list",IF(F13="Yes","STOP: error 56000, an endorsement is already in progress",IF(H13=0,"SKIP: fee already 0.000","PROCEED: set VAT Inclusive fee to 0"))) -> PROCEED: set VAT Inclusive fee to 0 | L13: =IF(LEFT(K13,7)="PROCEED","ACTIVE POLICY > DRAFT ENDORSEMENT QUOTE > FINAL ENDORSEMENT QUOTE (Submitted) > Approved Endorsed Quote","No endorsement is raised") -> ACTIVE POLICY > DRAFT ENDORSEMENT QUOTE > FINAL ENDORSEMENT QUOTE (Submitted) > Approved Endorsed Quote | M13: =IF(LEFT(K13,7)<>"PROCEED","n/a",IF(I13="(blank)","Select Approved before Submit","Already Approved")) -> Already Approved | N13: =IF(LEFT(K13,7)="PROCEED",J13,"n/a") -> 03/08/2026
A14: 112045877001 | B14: ITUMELENG SELLO | C14: 8702177918086 | D14: 8702177918086 | E14: =IF(C14=D14,"MATCH","MISMATCH") -> MATCH | F14: No | H14: =INDEX('Fee Switch-Off'!$G$5:$G$30,MATCH($A14,'Fee Switch-Off'!$A$5:$A$30,0)) -> 0.92 | I14: Approved | J14: 30/07/2026 | K14: =IF(E14="MISMATCH","STOP: ID number does not match the work list",IF(F14="Yes","STOP: error 56000, an endorsement is already in progress",IF(H14=0,"SKIP: fee already 0.000","PROCEED: set VAT Inclusive fee to 0"))) -> PROCEED: set VAT Inclusive fee to 0 | L14: =IF(LEFT(K14,7)="PROCEED","ACTIVE POLICY > DRAFT ENDORSEMENT QUOTE > FINAL ENDORSEMENT QUOTE (Submitted) > Approved Endorsed Quote","No endorsement is raised") -> ACTIVE POLICY > DRAFT ENDORSEMENT QUOTE > FINAL ENDORSEMENT QUOTE (Submitted) > Approved Endorsed Quote | M14: =IF(LEFT(K14,7)<>"PROCEED","n/a",IF(I14="(blank)","Select Approved before Submit","Already Approved")) -> Already Approved | N14: =IF(LEFT(K14,7)="PROCEED",J14,"n/a") -> 30/07/2026
A15: 112476310001 | B15: CHANTEL VAN WYK | C15: 7504043307085 | D15: 7504043307085 | E15: =IF(C15=D15,"MATCH","MISMATCH") -> MATCH | F15: No | H15: =INDEX('Fee Switch-Off'!$G$5:$G$30,MATCH($A15,'Fee Switch-Off'!$A$5:$A$30,0)) -> 1.725 | I15: Approved | J15: 04/08/2026 | K15: =IF(E15="MISMATCH","STOP: ID number does not match the work list",IF(F15="Yes","STOP: error 56000, an endorsement is already in progress",IF(H15=0,"SKIP: fee already 0.000","PROCEED: set VAT Inclusive fee to 0"))) -> PROCEED: set VAT Inclusive fee to 0 | L15: =IF(LEFT(K15,7)="PROCEED","ACTIVE POLICY > DRAFT ENDORSEMENT QUOTE > FINAL ENDORSEMENT QUOTE (Submitted) > Approved Endorsed Quote","No endorsement is raised") -> ACTIVE POLICY > DRAFT ENDORSEMENT QUOTE > FINAL ENDORSEMENT QUOTE (Submitted) > Approved Endorsed Quote | M15: =IF(LEFT(K15,7)<>"PROCEED","n/a",IF(I15="(blank)","Select Approved before Submit","Already Approved")) -> Already Approved | N15: =IF(LEFT(K15,7)="PROCEED",J15,"n/a") -> 04/08/2026
A16: 112718459001 | B16: MPHO DLAMINI | C16: 9612218696089 | D16: 9612218696089 | E16: =IF(C16=D16,"MATCH","MISMATCH") -> MATCH | F16: No | H16: =INDEX('Fee Switch-Off'!$G$5:$G$30,MATCH($A16,'Fee Switch-Off'!$A$5:$A$30,0)) -> 0.345 | I16: Approved | J16: 01/08/2026 | K16: =IF(E16="MISMATCH","STOP: ID number does not match the work list",IF(F16="Yes","STOP: error 56000, an endorsement is already in progress",IF(H16=0,"SKIP: fee already 0.000","PROCEED: set VAT Inclusive fee to 0"))) -> PROCEED: set VAT Inclusive fee to 0 | L16: =IF(LEFT(K16,7)="PROCEED","ACTIVE POLICY > DRAFT ENDORSEMENT QUOTE > FINAL ENDORSEMENT QUOTE (Submitted) > Approved Endorsed Quote","No endorsement is raised") -> ACTIVE POLICY > DRAFT ENDORSEMENT QUOTE > FINAL ENDORSEMENT QUOTE (Submitted) > Approved Endorsed Quote | M16: =IF(LEFT(K16,7)<>"PROCEED","n/a",IF(I16="(blank)","Select Approved before Submit","Already Approved")) -> Already Approved | N16: =IF(LEFT(K16,7)="PROCEED",J16,"n/a") -> 01/08/2026
... A21: 113845106001 | B21: ZANELE DUBE | C21: 9202090641088 | D21: 9202090641088 | E21: =IF(C21=D21,"MATCH","MISMATCH") -> MATCH | F21: No | H21: =INDEX('Fee Switch-Off'!$G$5:$G$30,MATCH($A21,'Fee Switch-Off'!$A$5:$A$30,0)) -> 0 | I21: Approved | J21: 01/08/2026 | K21: =IF(E21="MISMATCH","STOP: ID number does not match the work list",IF(F21="Yes","STOP: error 56000, an endorsement is already in progress",IF(H21=0,"SKIP: fee already 0.000","PROCEED: set VAT Inclusive fee to 0"))) -> SKIP: fee already 0.000 | L21: =IF(LEFT(K21,7)="PROCEED","ACTIVE POLICY > DRAFT ENDORSEMENT QUOTE > FINAL ENDORSEMENT QUOTE (Submitted) > Approved Endorsed Quote","No endorsement is raised") -> No endorsement is raised | M21: =IF(LEFT(K21,7)<>"PROCEED","n/a",IF(I21="(blank)","Select Approved before Submit","Already Approved")) -> n/a | N21: =IF(LEFT(K21,7)="PROCEED",J21,"n/a") -> n/a
A22: 113901377001 | B22: LUNGILE NGCOBO | C22: 8106236030083 | D22: 8106236030083 | E22: =IF(C22=D22,"MATCH","MISMATCH") -> MATCH | F22: Yes | G22: Quote 1139013770010001: FINAL ENDORSEMENT QUOTE, effective 01/11/2026 | H22: =INDEX('Fee Switch-Off'!$G$5:$G$30,MATCH($A22,'Fee Switch-Off'!$A$5:$A$30,0)) -> 0.575 | I22: Approved | J22: 31/07/2026 | K22: =IF(E22="MISMATCH","STOP: ID number does not match the work list",IF(F22="Yes","STOP: error 56000, an endorsement is already in progress",IF(H22=0,"SKIP: fee already 0.000","PROCEED: set VAT Inclusive fee to 0"))) -> STOP: error 56000, an endorsement is already in progress | L22: =IF(LEFT(K22,7)="PROCEED","ACTIVE POLICY > DRAFT ENDORSEMENT QUOTE > FINAL ENDORSEMENT QUOTE (Submitted) > Approved Endorsed Quote","No endorsement is raised") -> No endorsement is raised | M22: =IF(LEFT(K22,7)<>"PROCEED","n/a",IF(I22="(blank)","Select Approved before Submit","Already Approved")) -> n/a | N22: =IF(LEFT(K22,7)="PROCEED",J22,"n/a") -> n/a
A23: 114020658001 | B23: MEGAN FOURIE | C23: 8510031419088 | D23: 8510031419088 | E23: =IF(C23=D23,"MATCH","MISMATCH") -> MATCH | F23: Yes | G23: Quote 1140206580010001: DRAFT ENDORSEMENT QUOTE | H23: =INDEX('Fee Switch-Off'!$G$5:$G$30,MATCH($A23,'Fee Switch-Off'!$A$5:$A$30,0)) -> 1.15 | I23: Approved | J23: 03/08/2026 | K23: =IF(E23="MISMATCH","STOP: ID number does not match the work list",IF(F23="Yes","STOP: error 56000, an endorsement is already in progress",IF(H23=0,"SKIP: fee already 0.000","PROCEED: set VAT Inclusive fee to 0"))) -> STOP: error 56000, an endorsement is already in progress | L23: =IF(LEFT(K23,7)="PROCEED","ACTIVE POLICY > DRAFT ENDORSEMENT QUOTE > FINAL ENDORSEMENT QUOTE (Submitted) > Approved Endorsed Quote","No endorsement is raised") -> No endorsement is raised | M23: =IF(LEFT(K23,7)<>"PROCEED","n/a",IF(I23="(blank)","Select Approved before Submit","Already Approved")) -> n/a | N23: =IF(LEFT(K23,7)="PROCEED",J23,"n/a") -> n/a
A24: 114137290001 | B24: TSHEPO MASEKO | C24: 8002286808082 | D24: 8002286817083 | E24: =IF(C24=D24,"MATCH","MISMATCH") -> MISMATCH | F24: No | H24: =INDEX('Fee Switch-Off'!$G$5:$G$30,MATCH($A24,'Fee Switch-Off'!$A$5:$A$30,0)) -> 1.15 | I24: Approved | J24: 30/07/2026 | K24: =IF(E24="MISMATCH","STOP: ID number does not match the work list",IF(F24="Yes","STOP: error 56000, an endorsement is already in progress",IF(H24=0,"SKIP: fee already 0.000","PROCEED: set VAT Inclusive fee to 0"))) -> STOP: ID number does not match the work list | L24: =IF(LEFT(K24,7)="PROCEED","ACTIVE POLICY > DRAFT ENDORSEMENT QUOTE > FINAL ENDORSEMENT QUOTE (Submitted) > Approved Endorsed Quote","No endorsement is raised") -> No endorsement is raised | M24: =IF(LEFT(K24,7)<>"PROCEED","n/a",IF(I24="(blank)","Select Approved before Submit","Already Approved")) -> n/a | N24: =IF(LEFT(K24,7)="PROCEED",J24,"n/a") -> n/a
A25: 114250817001 | B25: NOMPUMELELO SHABALALA | C25: 9107122197084 | D25: 9107122197084 | E25: =IF(C25=D25,"MATCH","MISMATCH") -> MATCH | F25: No | H25: =INDEX('Fee Switch-Off'!$G$5:$G$30,MATCH($A25,'Fee Switch-Off'!$A$5:$A$30,0)) -> 0.575 | I25: (blank) | J25: 04/08/2026 | K25: =IF(E25="MISMATCH","STOP: ID number does not match the work list",IF(F25="Yes","STOP: error 56000, an endorsement is already in progress",IF(H25=0,"SKIP: fee already 0.000","PROCEED: set VAT Inclusive fee to 0"))) -> PROCEED: set VAT Inclusive fee to 0 | L25: =IF(LEFT(K25,7)="PROCEED","ACTIVE POLICY > DRAFT ENDORSEMENT QUOTE > FINAL ENDORSEMENT QUOTE (Submitted) > Approved Endorsed Quote","No endorsement is raised") -> ACTIVE POLICY > DRAFT ENDORSEMENT QUOTE > FINAL ENDORSEMENT QUOTE (Submitted) > Approved Endorsed Quote | M25: =IF(LEFT(K25,7)<>"PROCEED","n/a",IF(I25="(blank)","Select Approved before Submit","Already Approved")) -> Select Approved before Submit | N25: =IF(LEFT(K25,7)="PROCEED",J25,"n/a") -> 04/08/2026
A26: 114318964001 | B26: GARETH NAIDOO | C26: 7504077586083 | D26: 7504077586083 | E26: =IF(C26=D26,"MATCH","MISMATCH") -> MATCH | F26: No | H26: =INDEX('Fee Switch-Off'!$G$5:$G$30,MATCH($A26,'Fee Switch-Off'!$A$5:$A$30,0)) -> 1.15 | I26: (blank) | J26: 01/08/2026 | K26: =IF(E26="MISMATCH","STOP: ID number does not match the work list",IF(F26="Yes","STOP: error 56000, an endorsement is already in progress",IF(H26=0,"SKIP: fee already 0.000","PROCEED: set VAT Inclusive fee to 0"))) -> PROCEED: set VAT Inclusive fee to 0 | L26: =IF(LEFT(K26,7)="PROCEED","ACTIVE POLICY > DRAFT ENDORSEMENT QUOTE > FINAL ENDORSEMENT QUOTE (Submitted) > Approved Endorsed Quote","No endorsement is raised") -> ACTIVE POLICY > DRAFT ENDORSEMENT QUOTE > FINAL ENDORSEMENT QUOTE (Submitted) > Approved Endorsed Quote | M26: =IF(LEFT(K26,7)<>"PROCEED","n/a",IF(I26="(blank)","Select Approved before Submit","Already Approved")) -> Select Approved before Submit | N26: =IF(LEFT(K26,7)="PROCEED",J26,"n/a") -> 01/08/2026
A27: 114561023001 | B27: BUSISIWE MTHEMBU | C27: 8401152975084 | D27: 8401152975084 | E27: =IF(C27=D27,"MATCH","MISMATCH") -> MATCH | F27: No | H27: =INDEX('Fee Switch-Off'!$G$5:$G$30,MATCH($A27,'Fee Switch-Off'!$A$5:$A$30,0)) -> 1.15 | I27: Approved | J27: 31/07/2026 | K27: =IF(E27="MISMATCH","STOP: ID number does not match the work list",IF(F27="Yes","STOP: error 56000, an endorsement is already in progress",IF(H27=0,"SKIP: fee already 0.000","PROCEED: set VAT Inclusive fee to 0"))) -> PROCEED: set VAT Inclusive fee to 0 | L27: =IF(LEFT(K27,7)="PROCEED","ACTIVE POLICY > DRAFT ENDORSEMENT QUOTE > FINAL ENDORSEMENT QUOTE (Submitted) > Approved Endorsed Quote","No endorsement is raised") -> ACTIVE POLICY > DRAFT ENDORSEMENT QUOTE > FINAL ENDORSEMENT QUOTE (Submitted) > Approved Endorsed Quote | M27: =IF(LEFT(K27,7)<>"PROCEED","n/a",IF(I27="(blank)","Select Approved before Submit","Already Approved")) -> Already Approved | N27: =IF(LEFT(K27,7)="PROCEED",J27,"n/a") -> 31/07/2026
A28: 114602745001 | B28: ANDRE DU PLESSIS | C28: 7009218364085 | D28: 7009218364085 | E28: =IF(C28=D28,"MATCH","MISMATCH") -> MATCH | F28: No | H28: =INDEX('Fee Switch-Off'!$G$5:$G$30,MATCH($A28,'Fee Switch-Off'!$A$5:$A$30,0)) -> 1.15 | I28: Approved | J28: 03/08/2026 | K28: =IF(E28="MISMATCH","STOP: ID number does not match the work list",IF(F28="Yes","STOP: error 56000, an endorsement is already in progress",IF(H28=0,"SKIP: fee already 0.000","PROCEED: set VAT Inclusive fee to 0"))) -> PROCEED: set VAT Inclusive fee to 0 | L28: =IF(LEFT(K28,7)="PROCEED","ACTIVE POLICY > DRAFT ENDORSEMENT QUOTE > FINAL ENDORSEMENT QUOTE (Submitted) > Approved Endorsed Quote","No endorsement is raised") -> ACTIVE POLICY > DRAFT ENDORSEMENT QUOTE > FINAL ENDORSEMENT QUOTE (Submitted) > Approved Endorsed Quote | M28: =IF(LEFT(K28,7)<>"PROCEED","n/a",IF(I28="(blank)","Select Approved before Submit","Already Approved")) -> Already Approved | N28: =IF(LEFT(K28,7)="PROCEED",J28,"n/a") -> 03/08/2026
A29: 114688139001 | B29: PALESA RADEBE | C29: 8912043753084 | D29: 8912043753084 | E29: =IF(C29=D29,"MATCH","MISMATCH") -> MATCH | F29: No | H29: =INDEX('Fee Switch-Off'!$G$5:$G$30,MATCH($A29,'Fee Switch-Off'!$A$5:$A$30,0)) -> 0.575 | I29: Approved | J29: 30/07/2026 | K29: =IF(E29="MISMATCH","STOP: ID number does not match the work list",IF(F29="Yes","STOP: error 56000, an endorsement is already in progress",IF(H29=0,"SKIP: fee already 0.000","PROCEED: set VAT Inclusive fee to 0"))) -> PROCEED: set VAT Inclusive fee to 0 | L29: =IF(LEFT(K29,7)="PROCEED","ACTIVE POLICY > DRAFT ENDORSEMENT QUOTE > FINAL ENDORSEMENT QUOTE (Submitted) > Approved Endorsed Quote","No endorsement is raised") -> ACTIVE POLICY > DRAFT ENDORSEMENT QUOTE > FINAL ENDORSEMENT QUOTE (Submitted) > Approved Endorsed Quote | M29: =IF(LEFT(K29,7)<>"PROCEED","n/a",IF(I29="(blank)","Select Approved before Submit","Already Approved")) -> Already Approved | N29: =IF(LEFT(K29,7)="PROCEED",J29,"n/a") -> 30/07/2026
A30: 114723506001 | B30: RUBEN PILLAY | C30: 8605189142084 | D30: 8605189142084 | E30: =IF(C30=D30,"MATCH","MISMATCH") -> MATCH | F30: No | H30: =INDEX('Fee Switch-Off'!$G$5:$G$30,MATCH($A30,'Fee Switch-Off'!$A$5:$A$30,0)) -> 1.15 | I30: Approved | J30: 04/08/2026 | K30: =IF(E30="MISMATCH","STOP: ID number does not match the work list",IF(F30="Yes","STOP: error 56000, an endorsement is already in progress",IF(H30=0,"SKIP: fee already 0.000","PROCEED: set VAT Inclusive fee to 0"))) -> PROCEED: set VAT Inclusive fee to 0 | L30: =IF(LEFT(K30,7)="PROCEED","ACTIVE POLICY > DRAFT ENDORSEMENT QUOTE > FINAL ENDORSEMENT QUOTE (Submitted) > Approved Endorsed Quote","No endorsement is raised") -> ACTIVE POLICY > DRAFT ENDORSEMENT QUOTE > FINAL ENDORSEMENT QUOTE (Submitted) > Approved Endorsed Quote | M30: =IF(LEFT(K30,7)<>"PROCEED","n/a",IF(I30="(blank)","Select Approved before Submit","Already Approved")) -> Already Approved | N30: =IF(LEFT(K30,7)="PROCEED",J30,"n/a") -> 04/08/2026
A32: Summary
B33: Policies the process will change | C33: =COUNTIF($K$5:$K$30,"PROCEED*") -> 20
B34: Skipped: fee already 0.000 | C34: =COUNTIF($K$5:$K$30,"SKIP*") -> 3
B35: Stopped: ID mismatch or error 56000 | C35: =COUNTIF($K$5:$K$30,"STOP*") -> 3

Sheet Split Fee
A1: Split Fee: the new VAT Inclusive fee when the staying adviser keeps a share
A2: Yellow = the staying adviser's asset advice fee share (%). New fee = current fee x share, rounded down to 3 decimals. The first two rows are the SOP's own example and the 60/40 case.
A4: Contract No. | B4: Client | C4: Note | D4: Market value (R) | E4: VAT Inclusive fee now (%) | F4: Staying adviser share (%) | G4: Other adviser(s) share (%) | H4: New VAT Inclusive fee (%) | I4: New VAT Exclusive fee (%) | J4: Fee a year before (R) | K4: Fee a year after (R) | L4: Reduction a year (R)
A5: 119900001001 | B5: =INDEX('Fee Switch-Off'!$B$5:$B$30,MATCH($A5,'Fee Switch-Off'!$A$5:$A$30,0)) -> NOKUTHULA MAHLOBO | C5: SOP example: 50 / 50 | D5: =INDEX('Fee Switch-Off'!$E$5:$E$30,MATCH($A5,'Fee Switch-Off'!$A$5:$A$30,0)) -> 4323.48 | E5: =INDEX('Fee Switch-Off'!$G$5:$G$30,MATCH($A5,'Fee Switch-Off'!$A$5:$A$30,0)) -> 0.575 | F5: 50 | G5: =100-F5 -> 50 | H5: =ROUNDDOWN(E5*F5/100+1E-9,3) -> 0.287 | I5: =ROUND(H5/Assumptions!$B$3+1E-9,3) -> 0.25 | J5: =ROUND(D5*E5/100+1E-9,2) -> 24.86 | K5: =ROUND(D5*H5/100+1E-9,2) -> 12.41 | L5: =J5-K5 -> 12.45
A6: 119900001001 | B6: =INDEX('Fee Switch-Off'!$B$5:$B$30,MATCH($A6,'Fee Switch-Off'!$A$5:$A$30,0)) -> NOKUTHULA MAHLOBO | C6: 60 / 40 split | D6: =INDEX('Fee Switch-Off'!$E$5:$E$30,MATCH($A6,'Fee Switch-Off'!$A$5:$A$30,0)) -> 4323.48 | E6: =INDEX('Fee Switch-Off'!$G$5:$G$30,MATCH($A6,'Fee Switch-Off'!$A$5:$A$30,0)) -> 0.575 | F6: 60 | G6: =100-F6 -> 40 | H6: =ROUNDDOWN(E6*F6/100+1E-9,3) -> 0.345 | I6: =ROUND(H6/Assumptions!$B$3+1E-9,3) -> 0.3 | J6: =ROUND(D6*E6/100+1E-9,2) -> 24.86 | K6: =ROUND(D6*H6/100+1E-9,2) -> 14.92 | L6: =J6-K6 -> 9.94
A7: 110671307001 | B7: =INDEX('Fee Switch-Off'!$B$5:$B$30,MATCH($A7,'Fee Switch-Off'!$A$5:$A$30,0)) -> SIPHO KHUMALO | C7: Single adviser, split 50 / 50 | D7: =INDEX('Fee Switch-Off'!$E$5:$E$30,MATCH($A7,'Fee Switch-Off'!$A$5:$A$30,0)) -> 84450 | E7: =INDEX('Fee Switch-Off'!$G$5:$G$30,MATCH($A7,'Fee Switch-Off'!$A$5:$A$30,0)) -> 1.15 | F7: 50 | G7: =100-F7 -> 50 | H7: =ROUNDDOWN(E7*F7/100+1E-9,3) -> 0.575 | I7: =ROUND(H7/Assumptions!$B$3+1E-9,3) -> 0.5 | J7: =ROUND(D7*E7/100+1E-9,2) -> 971.18 | K7: =ROUND(D7*H7/100+1E-9,2) -> 485.59 | L7: =J7-K7 -> 485.59
A8: 112333103001 | B8: =INDEX('Fee Switch-Off'!$B$5:$B$30,MATCH($A8,'Fee Switch-Off'!$A$5:$A$30,0)) -> THANDEKA ZULU | C8: Single adviser, split 50 / 50 | D8: =INDEX('Fee Switch-Off'!$E$5:$E$30,MATCH($A8,'Fee Switch-Off'!$A$5:$A$30,0)) -> 36074.16 | E8: =INDEX('Fee Switch-Off'!$G$5:$G$30,MATCH($A8,'Fee Switch-Off'!$A$5:$A$30,0)) -> 0.863 | F8: 50 | G8: =100-F8 -> 50 | H8: =ROUNDDOWN(E8*F8/100+1E-9,3) -> 0.431 | I8: =ROUND(H8/Assumptions!$B$3+1E-9,3) -> 0.375 | J8: =ROUND(D8*E8/100+1E-9,2) -> 311.32 | K8: =ROUND(D8*H8/100+1E-9,2) -> 155.48 | L8: =J8-K8 -> 155.84
A9: 112953094001 | B9: =INDEX('Fee Switch-Off'!$B$5:$B$30,MATCH($A9,'Fee Switch-Off'!$A$5:$A$30,0)) -> RIAAN STEYN | C9: Single adviser, split 50 / 50 | D9: =INDEX('Fee Switch-Off'!$E$5:$E$30,MATCH($A9,'Fee Switch-Off'!$A$5:$A$30,0)) -> 75665.4 | E9: =INDEX('Fee Switch-Off'!$G$5:$G$30,MATCH($A9,'Fee Switch-Off'!$A$5:$A$30,0)) -> 0.575 | F9: 50 | G9: =100-F9 -> 50 | H9: =ROUNDDOWN(E9*F9/100+1E-9,3) -> 0.287 | I9: =ROUND(H9/Assumptions!$B$3+1E-9,3) -> 0.25 | J9: =ROUND(D9*E9/100+1E-9,2) -> 435.08 | K9: =ROUND(D9*H9/100+1E-9,2) -> 217.16 | L9: =J9-K9 -> 217.92
A10: 113162231001 | B10: =INDEX('Fee Switch-Off'!$B$5:$B$30,MATCH($A10,'Fee Switch-Off'!$A$5:$A$30,0)) -> AYESHA PATEL | C10: Single adviser, split 50 / 50 | D10: =INDEX('Fee Switch-Off'!$E$5:$E$30,MATCH($A10,'Fee Switch-Off'!$A$5:$A$30,0)) -> 92322.9 | E10: =INDEX('Fee Switch-Off'!$G$5:$G$30,MATCH($A10,'Fee Switch-Off'!$A$5:$A$30,0)) -> 1.438 | F10: 50 | G10: =100-F10 -> 50 | H10: =ROUNDDOWN(E10*F10/100+1E-9,3) -> 0.719 | I10: =ROUND(H10/Assumptions!$B$3+1E-9,3) -> 0.625 | J10: =ROUND(D10*E10/100+1E-9,2) -> 1327.6 | K10: =ROUND(D10*H10/100+1E-9,2) -> 663.8 | L10: =J10-K10 -> 663.8
A11: 113165622001 | B11: =INDEX('Fee Switch-Off'!$B$5:$B$30,MATCH($A11,'Fee Switch-Off'!$A$5:$A$30,0)) -> KAGISO MOLEFE | C11: Single adviser, split 50 / 50 | D11: =INDEX('Fee Switch-Off'!$E$5:$E$30,MATCH($A11,'Fee Switch-Off'!$A$5:$A$30,0)) -> 30774.3 | E11: =INDEX('Fee Switch-Off'!$G$5:$G$30,MATCH($A11,'Fee Switch-Off'!$A$5:$A$30,0)) -> 1.15 | F11: 50 | G11: =100-F11 -> 50 | H11: =ROUNDDOWN(E11*F11/100+1E-9,3) -> 0.575 | I11: =ROUND(H11/Assumptions!$B$3+1E-9,3) -> 0.5 | J11: =ROUND(D11*E11/100+1E-9,2) -> 353.9 | K11: =ROUND(D11*H11/100+1E-9,2) -> 176.95 | L11: =J11-K11 -> 176.95
A12: 113402518001 | B12: =INDEX('Fee Switch-Off'!$B$5:$B$30,MATCH($A12,'Fee Switch-Off'!$A$5:$A$30,0)) -> CHARLENE ADAMS | C12: Single adviser, split 50 / 50 | D12: =INDEX('Fee Switch-Off'!$E$5:$E$30,MATCH($A12,'Fee Switch-Off'!$A$5:$A$30,0)) -> 18213.8 | E12: =INDEX('Fee Switch-Off'!$G$5:$G$30,MATCH($A12,'Fee Switch-Off'!$A$5:$A$30,0)) -> 0.69 | F12: 50 | G12: =100-F12 -> 50 | H12: =ROUNDDOWN(E12*F12/100+1E-9,3) -> 0.345 | I12: =ROUND(H12/Assumptions!$B$3+1E-9,3) -> 0.3 | J12: =ROUND(D12*E12/100+1E-9,2) -> 125.68 | K12: =ROUND(D12*H12/100+1E-9,2) -> 62.84 | L12: =J12-K12 -> 62.84
A13: 113577840001 | B13: =INDEX('Fee Switch-Off'!$B$5:$B$30,MATCH($A13,'Fee Switch-Off'!$A$5:$A$30,0)) -> BONGANI MAHLANGU | C13: Single adviser, split 50 / 50 | D13: =INDEX('Fee Switch-Off'!$E$5:$E$30,MATCH($A13,'Fee Switch-Off'!$A$5:$A$30,0)) -> 29646.4 | E13: =INDEX('Fee Switch-Off'!$G$5:$G$30,MATCH($A13,'Fee Switch-Off'!$A$5:$A$30,0)) -> 1.035 | F13: 50 | G13: =100-F13 -> 50 | H13: =ROUNDDOWN(E13*F13/100+1E-9,3) -> 0.517 | I13: =ROUND(H13/Assumptions!$B$3+1E-9,3) -> 0.45 | J13: =ROUND(D13*E13/100+1E-9,2) -> 306.84 | K13: =ROUND(D13*H13/100+1E-9,2) -> 153.27 | L13: =J13-K13 -> 153.57
A14: 111890254001 | B14: =INDEX('Fee Switch-Off'!$B$5:$B$30,MATCH($A14,'Fee Switch-Off'!$A$5:$A$30,0)) -> FATIMA OSMAN | C14: Single adviser, split 50 / 50 | D14: =INDEX('Fee Switch-Off'!$E$5:$E$30,MATCH($A14,'Fee Switch-Off'!$A$5:$A$30,0)) -> 149814 | E14: =INDEX('Fee Switch-Off'!$G$5:$G$30,MATCH($A14,'Fee Switch-Off'!$A$5:$A$30,0)) -> 0.46 | F14: 50 | G14: =100-F14 -> 50 | H14: =ROUNDDOWN(E14*F14/100+1E-9,3) -> 0.23 | I14: =ROUND(H14/Assumptions!$B$3+1E-9,3) -> 0.2 | J14: =ROUND(D14*E14/100+1E-9,2) -> 689.14 | K14: =ROUND(D14*H14/100+1E-9,2) -> 344.57 | L14: =J14-K14 -> 344.57
A15: 112045877001 | B15: =INDEX('Fee Switch-Off'!$B$5:$B$30,MATCH($A15,'Fee Switch-Off'!$A$5:$A$30,0)) -> ITUMELENG SELLO | C15: Single adviser, split 50 / 50 | D15: =INDEX('Fee Switch-Off'!$E$5:$E$30,MATCH($A15,'Fee Switch-Off'!$A$5:$A$30,0)) -> 88935.84 | E15: =INDEX('Fee Switch-Off'!$G$5:$G$30,MATCH($A15,'Fee Switch-Off'!$A$5:$A$30,0)) -> 0.92 | F15: 50 | G15: =100-F15 -> 50 | H15: =ROUNDDOWN(E15*F15/100+1E-9,3) -> 0.46 | I15: =ROUND(H15/Assumptions!$B$3+1E-9,3) -> 0.4 | J15: =ROUND(D15*E15/100+1E-9,2) -> 818.21 | K15: =ROUND(D15*H15/100+1E-9,2) -> 409.1 | L15: =J15-K15 -> 409.11
A16: 112476310001 | B16: =INDEX('Fee Switch-Off'!$B$5:$B$30,MATCH($A16,'Fee Switch-Off'!$A$5:$A$30,0)) -> CHANTEL VAN WYK | C16: Single adviser, split 50 / 50 | D16: =INDEX('Fee Switch-Off'!$E$5:$E$30,MATCH($A16,'Fee Switch-Off'!$A$5:$A$30,0)) -> 140507.5 | E16: =INDEX('Fee Switch-Off'!$G$5:$G$30,MATCH($A16,'Fee Switch-Off'!$A$5:$A$30,0)) -> 1.725 | F16: 50 | G16: =100-F16 -> 50 | H16: =ROUNDDOWN(E16*F16/100+1E-9,3) -> 0.862 | I16: =ROUND(H16/Assumptions!$B$3+1E-9,3) -> 0.75 | J16: =ROUND(D16*E16/100+1E-9,2) -> 2423.75 | K16: =ROUND(D16*H16/100+1E-9,2) -> 1211.17 | L16: =J16-K16 -> 1212.58
... A19: 113290536001 | B19: =INDEX('Fee Switch-Off'!$B$5:$B$30,MATCH($A19,'Fee Switch-Off'!$A$5:$A$30,0)) -> DEON BEKKER | C19: Single adviser, split 50 / 50 | D19: =INDEX('Fee Switch-Off'!$E$5:$E$30,MATCH($A19,'Fee Switch-Off'!$A$5:$A$30,0)) -> 42593.76 | E19: =INDEX('Fee Switch-Off'!$G$5:$G$30,MATCH($A19,'Fee Switch-Off'!$A$5:$A$30,0)) -> 1.265 | F19: 50 | G19: =100-F19 -> 50 | H19: =ROUNDDOWN(E19*F19/100+1E-9,3) -> 0.632 | I19: =ROUND(H19/Assumptions!$B$3+1E-9,3) -> 0.55 | J19: =ROUND(D19*E19/100+1E-9,2) -> 538.81 | K19: =ROUND(D19*H19/100+1E-9,2) -> 269.19 | L19: =J19-K19 -> 269.62

Sheet Latency Budget
A1: Latency Budget: where a full case spends its time
A2: Seconds come from the latency table on the BaNCS login page. Policy search happens twice per case (capture and verification). Suggested timeout = Stress x 1.5, so a bot that gives up earlier than this will fail on a slow day.
A4: Step | B4: Observed in the recording | C4: Normal (s) | D4: Stress (s) | E4: Times per case | F4: Normal total (s) | G4: Stress total (s) | H4: Suggested timeout (s)
A5: Policy search → results | B5: A few seconds | C5: 2 | D5: 6 | E5: 2 | F5: =C5*E5 -> 4 | G5: =D5*E5 -> 12 | H5: =ROUNDUP(D5*1.5,0) -> 9
A6: Endorse/Alter → initiation screen opens | B6: Short | C6: 3 | D6: 10 | E6: 1 | F6: =C6*E6 -> 3 | G6: =D6*E6 -> 10 | H6: =ROUNDUP(D6*1.5,0) -> 15
A7: Save on the initiation screen | B7: Noticeable | C7: 5 | D7: 15 | E7: 1 | F7: =C7*E7 -> 5 | G7: =D7*E7 -> 15 | H7: =ROUNDUP(D7*1.5,0) -> 23
A8: Basic Details SAVE | B8: Noticeable | C8: 5 | D8: 15 | E8: 1 | F8: =C8*E8 -> 5 | G8: =D8*E8 -> 15 | H8: =ROUNDUP(D8*1.5,0) -> 23
A9: Create or Refresh Layer | B9: The longest single wait, around a minute and a half | C9: 30 | D9: 90 | E9: 1 | F9: =C9*E9 -> 30 | G9: =D9*E9 -> 90 | H9: =ROUNDUP(D9*1.5,0) -> 135
A10: Calculate Premium | B10: Around forty seconds | C10: 25 | D10: 75 | E10: 1 | F10: =C10*E10 -> 25 | G10: =D10*E10 -> 75 | H10: =ROUNDUP(D10*1.5,0) -> 113
A11: End Sub Endorsement | B11: Around half a minute | C11: 10 | D11: 30 | E11: 1 | F11: =C11*E11 -> 10 | G11: =D11*E11 -> 30 | H11: =ROUNDUP(D11*1.5,0) -> 45
A12: Lock EBQ | B12: Over a minute | C12: 20 | D12: 60 | E12: 1 | F12: =C12*E12 -> 20 | G12: =D12*E12 -> 60 | H12: =ROUNDUP(D12*1.5,0) -> 90
A13: Finalise Endorsement | B13: Noticeable | C13: 15 | D13: 45 | E13: 1 | F13: =C13*E13 -> 15 | G13: =D13*E13 -> 45 | H13: =ROUNDUP(D13*1.5,0) -> 68
A14: Endr Quote Submission → Submit | B14: Around half a minute | C14: 20 | D14: 60 | E14: 1 | F14: =C14*E14 -> 20 | G14: =D14*E14 -> 60 | H14: =ROUNDUP(D14*1.5,0) -> 90
A15: Activate (closed book) | B15: Around half a minute | C15: 20 | D15: 60 | E15: 1 | F15: =C15*E15 -> 20 | G15: =D15*E15 -> 60 | H15: =ROUNDUP(D15*1.5,0) -> 90
A17: One full case | F17: =SUM(F5:F15) -> 157 | G17: =SUM(G5:G15) -> 472
A18: In minutes | F18: =ROUND(F17/60,1) -> 2.6 | G18: =ROUND(G17/60,1) -> 7.9
A19: Longest single wait (Stress) | G19: =MAX(D5:D15) -> 90

Sheet Quote Summary
A1: Quote Summary: what Calculate Premium shows on Endr Quote Summary
A2: The fee refund (or collection), the adviser commission and the clawback, worked out from the fee change on the Fee Switch-Off sheet (its New VAT Inclusive fee column). Same method as BaNCS: see the README sheet and Assumptions.
A4: Contract No. | B4: Client | C4: Market value (R) | D4: VAT Inclusive fee now (%) | E4: New VAT Inclusive fee (%) | F4: Fee a year before (R) | G4: Fee a year after (R) | H4: Fee a month before (R) | I4: Fee a month after (R) | J4: Monthly fee difference (R) | K4: Next due date | L4: Previous due date | M4: Days in fee period | N4: Effective date | O4: Days left in period | P4: Refund to client (R) | Q4: Collection from client (R) | R4: Commission scaling (%) | S4: Commission clawback (R) | T4: Adviser commission, rest of period (R) | U4: Ongoing (AAW) commission (%) | V4: Total endorsement premium (R) | W4: Commission payable immediately (R)
A5: 119900001001 | B5: =INDEX('Fee Switch-Off'!$B$5:$B$30,MATCH($A5,'Fee Switch-Off'!$A$5:$A$30,0)) -> NOKUTHULA MAHLOBO | C5: =INDEX('Fee Switch-Off'!$E$5:$E$30,MATCH($A5,'Fee Switch-Off'!$A$5:$A$30,0)) -> 4323.48 | D5: =INDEX('Fee Switch-Off'!$G$5:$G$30,MATCH($A5,'Fee Switch-Off'!$A$5:$A$30,0)) -> 0.575 | E5: =INDEX('Fee Switch-Off'!$K$5:$K$30,MATCH($A5,'Fee Switch-Off'!$A$5:$A$30,0)) -> 0 | F5: =ROUND(C5*D5/100+1E-9,2) -> 24.86 | G5: =ROUND(C5*E5/100+1E-9,2) -> 0 | H5: =ROUND(F5/Assumptions!$B$4+1E-9,2) -> 2.07 | I5: =ROUND(G5/Assumptions!$B$4+1E-9,2) -> 0 | J5: =ROUND(H5-I5+1E-9,2) -> 2.07 | K5: 46264 | L5: =EDATE(K5,-1) -> 46233 | M5: =K5-L5 -> 31 | N5: =Assumptions!$B$6 -> 46238 | O5: =MAX(0,MIN(M5,K5-N5)) -> 26 | P5: =IF(J5>0,ROUND(J5*O5/M5+1E-9,2),0) -> 1.74 | Q5: =IF(J5<0,ROUND(-J5*O5/M5+1E-9,2),0) -> 0 | R5: 100 | S5: =ROUND(P5/Assumptions!$B$3*R5/100+1E-9,2) -> 1.51 | T5: =ROUND(I5/Assumptions!$B$3*O5/M5*R5/100+1E-9,2) -> 0 | U5: =ROUND(E5/Assumptions!$B$3*R5/100+1E-9,3) -> 0 | V5: =INDEX('Fee Switch-Off'!$F$5:$F$30,MATCH($A5,'Fee Switch-Off'!$A$5:$A$30,0)) -> 600 | W5: =-S5 -> -1.51
A6: 110671307001 | B6: =INDEX('Fee Switch-Off'!$B$5:$B$30,MATCH($A6,'Fee Switch-Off'!$A$5:$A$30,0)) -> SIPHO KHUMALO | C6: =INDEX('Fee Switch-Off'!$E$5:$E$30,MATCH($A6,'Fee Switch-Off'!$A$5:$A$30,0)) -> 84450 | D6: =INDEX('Fee Switch-Off'!$G$5:$G$30,MATCH($A6,'Fee Switch-Off'!$A$5:$A$30,0)) -> 1.15 | E6: =INDEX('Fee Switch-Off'!$K$5:$K$30,MATCH($A6,'Fee Switch-Off'!$A$5:$A$30,0)) -> 0 | F6: =ROUND(C6*D6/100+1E-9,2) -> 971.18 | G6: =ROUND(C6*E6/100+1E-9,2) -> 0 | H6: =ROUND(F6/Assumptions!$B$4+1E-9,2) -> 80.93 | I6: =ROUND(G6/Assumptions!$B$4+1E-9,2) -> 0 | J6: =ROUND(H6-I6+1E-9,2) -> 80.93 | K6: 46246 | L6: =EDATE(K6,-1) -> 46215 | M6: =K6-L6 -> 31 | N6: =Assumptions!$B$6 -> 46238 | O6: =MAX(0,MIN(M6,K6-N6)) -> 8 | P6: =IF(J6>0,ROUND(J6*O6/M6+1E-9,2),0) -> 20.89 | Q6: =IF(J6<0,ROUND(-J6*O6/M6+1E-9,2),0) -> 0 | R6: 100 | S6: =ROUND(P6/Assumptions!$B$3*R6/100+1E-9,2) -> 18.17 | T6: =ROUND(I6/Assumptions!$B$3*O6/M6*R6/100+1E-9,2) -> 0 | U6: =ROUND(E6/Assumptions!$B$3*R6/100+1E-9,3) -> 0 | V6: =INDEX('Fee Switch-Off'!$F$5:$F$30,MATCH($A6,'Fee Switch-Off'!$A$5:$A$30,0)) -> 2500 | W6: =-S6 -> -18.17
A7: 112333103001 | B7: =INDEX('Fee Switch-Off'!$B$5:$B$30,MATCH($A7,'Fee Switch-Off'!$A$5:$A$30,0)) -> THANDEKA ZULU | C7: =INDEX('Fee Switch-Off'!$E$5:$E$30,MATCH($A7,'Fee Switch-Off'!$A$5:$A$30,0)) -> 36074.16 | D7: =INDEX('Fee Switch-Off'!$G$5:$G$30,MATCH($A7,'Fee Switch-Off'!$A$5:$A$30,0)) -> 0.863 | E7: =INDEX('Fee Switch-Off'!$K$5:$K$30,MATCH($A7,'Fee Switch-Off'!$A$5:$A$30,0)) -> 0 | F7: =ROUND(C7*D7/100+1E-9,2) -> 311.32 | G7: =ROUND(C7*E7/100+1E-9,2) -> 0 | H7: =ROUND(F7/Assumptions!$B$4+1E-9,2) -> 25.94 | I7: =ROUND(G7/Assumptions!$B$4+1E-9,2) -> 0 | J7: =ROUND(H7-I7+1E-9,2) -> 25.94 | K7: 46268 | L7: =EDATE(K7,-1) -> 46237 | M7: =K7-L7 -> 31 | N7: =Assumptions!$B$6 -> 46238 | O7: =MAX(0,MIN(M7,K7-N7)) -> 30 | P7: =IF(J7>0,ROUND(J7*O7/M7+1E-9,2),0) -> 25.1 | Q7: =IF(J7<0,ROUND(-J7*O7/M7+1E-9,2),0) -> 0 | R7: 100 | S7: =ROUND(P7/Assumptions!$B$3*R7/100+1E-9,2) -> 21.83 | T7: =ROUND(I7/Assumptions!$B$3*O7/M7*R7/100+1E-9,2) -> 0 | U7: =ROUND(E7/Assumptions!$B$3*R7/100+1E-9,3) -> 0 | V7: =INDEX('Fee Switch-Off'!$F$5:$F$30,MATCH($A7,'Fee Switch-Off'!$A$5:$A$30,0)) -> 1200 | W7: =-S7 -> -21.83
A8: 112953094001 | B8: =INDEX('Fee Switch-Off'!$B$5:$B$30,MATCH($A8,'Fee Switch-Off'!$A$5:$A$30,0)) -> RIAAN STEYN | C8: =INDEX('Fee Switch-Off'!$E$5:$E$30,MATCH($A8,'Fee Switch-Off'!$A$5:$A$30,0)) -> 75665.4 | D8: =INDEX('Fee Switch-Off'!$G$5:$G$30,MATCH($A8,'Fee Switch-Off'!$A$5:$A$30,0)) -> 0.575 | E8: =INDEX('Fee Switch-Off'!$K$5:$K$30,MATCH($A8,'Fee Switch-Off'!$A$5:$A$30,0)) -> 0 | F8: =ROUND(C8*D8/100+1E-9,2) -> 435.08 | G8: =ROUND(C8*E8/100+1E-9,2) -> 0 | H8: =ROUND(F8/Assumptions!$B$4+1E-9,2) -> 36.26 | I8: =ROUND(G8/Assumptions!$B$4+1E-9,2) -> 0 | J8: =ROUND(H8-I8+1E-9,2) -> 36.26 | K8: 46252 | L8: =EDATE(K8,-1) -> 46221 | M8: =K8-L8 -> 31 | N8: =Assumptions!$B$6 -> 46238 | O8: =MAX(0,MIN(M8,K8-N8)) -> 14 | P8: =IF(J8>0,ROUND(J8*O8/M8+1E-9,2),0) -> 16.38 | Q8: =IF(J8<0,ROUND(-J8*O8/M8+1E-9,2),0) -> 0 | R8: 100 | S8: =ROUND(P8/Assumptions!$B$3*R8/100+1E-9,2) -> 14.24 | T8: =ROUND(I8/Assumptions!$B$3*O8/M8*R8/100+1E-9,2) -> 0 | U8: =ROUND(E8/Assumptions!$B$3*R8/100+1E-9,3) -> 0 | V8: =INDEX('Fee Switch-Off'!$F$5:$F$30,MATCH($A8,'Fee Switch-Off'!$A$5:$A$30,0)) -> 3000 | W8: =-S8 -> -14.24
A9: 113162231001 | B9: =INDEX('Fee Switch-Off'!$B$5:$B$30,MATCH($A9,'Fee Switch-Off'!$A$5:$A$30,0)) -> AYESHA PATEL | C9: =INDEX('Fee Switch-Off'!$E$5:$E$30,MATCH($A9,'Fee Switch-Off'!$A$5:$A$30,0)) -> 92322.9 | D9: =INDEX('Fee Switch-Off'!$G$5:$G$30,MATCH($A9,'Fee Switch-Off'!$A$5:$A$30,0)) -> 1.438 | E9: =INDEX('Fee Switch-Off'!$K$5:$K$30,MATCH($A9,'Fee Switch-Off'!$A$5:$A$30,0)) -> 0 | F9: =ROUND(C9*D9/100+1E-9,2) -> 1327.6 | G9: =ROUND(C9*E9/100+1E-9,2) -> 0 | H9: =ROUND(F9/Assumptions!$B$4+1E-9,2) -> 110.63 | I9: =ROUND(G9/Assumptions!$B$4+1E-9,2) -> 0 | J9: =ROUND(H9-I9+1E-9,2) -> 110.63 | K9: 46241 | L9: =EDATE(K9,-1) -> 46210 | M9: =K9-L9 -> 31 | N9: =Assumptions!$B$6 -> 46238 | O9: =MAX(0,MIN(M9,K9-N9)) -> 3 | P9: =IF(J9>0,ROUND(J9*O9/M9+1E-9,2),0) -> 10.71 | Q9: =IF(J9<0,ROUND(-J9*O9/M9+1E-9,2),0) -> 0 | R9: 100 | S9: =ROUND(P9/Assumptions!$B$3*R9/100+1E-9,2) -> 9.31 | T9: =ROUND(I9/Assumptions!$B$3*O9/M9*R9/100+1E-9,2) -> 0 | U9: =ROUND(E9/Assumptions!$B$3*R9/100+1E-9,3) -> 0 | V9: =INDEX('Fee Switch-Off'!$F$5:$F$30,MATCH($A9,'Fee Switch-Off'!$A$5:$A$30,0)) -> 4500 | W9: =-S9 -> -9.31
A10: 113165622001 | B10: =INDEX('Fee Switch-Off'!$B$5:$B$30,MATCH($A10,'Fee Switch-Off'!$A$5:$A$30,0)) -> KAGISO MOLEFE | C10: =INDEX('Fee Switch-Off'!$E$5:$E$30,MATCH($A10,'Fee Switch-Off'!$A$5:$A$30,0)) -> 30774.3 | D10: =INDEX('Fee Switch-Off'!$G$5:$G$30,MATCH($A10,'Fee Switch-Off'!$A$5:$A$30,0)) -> 1.15 | E10: =INDEX('Fee Switch-Off'!$K$5:$K$30,MATCH($A10,'Fee Switch-Off'!$A$5:$A$30,0)) -> 0 | F10: =ROUND(C10*D10/100+1E-9,2) -> 353.9 | G10: =ROUND(C10*E10/100+1E-9,2) -> 0 | H10: =ROUND(F10/Assumptions!$B$4+1E-9,2) -> 29.49 | I10: =ROUND(G10/Assumptions!$B$4+1E-9,2) -> 0 | J10: =ROUND(H10-I10+1E-9,2) -> 29.49 | K10: 46243 | L10: =EDATE(K10,-1) -> 46212 | M10: =K10-L10 -> 31 | N10: =Assumptions!$B$6 -> 46238 | O10: =MAX(0,MIN(M10,K10-N10)) -> 5 | P10: =IF(J10>0,ROUND(J10*O10/M10+1E-9,2),0) -> 4.76 | Q10: =IF(J10<0,ROUND(-J10*O10/M10+1E-9,2),0) -> 0 | R10: 100 | S10: =ROUND(P10/Assumptions!$B$3*R10/100+1E-9,2) -> 4.14 | T10: =ROUND(I10/Assumptions!$B$3*O10/M10*R10/100+1E-9,2) -> 0 | U10: =ROUND(E10/Assumptions!$B$3*R10/100+1E-9,3) -> 0 | V10: =INDEX('Fee Switch-Off'!$F$5:$F$30,MATCH($A10,'Fee Switch-Off'!$A$5:$A$30,0)) -> 1500 | W10: =-S10 -> -4.14
A11: 113402518001 | B11: =INDEX('Fee Switch-Off'!$B$5:$B$30,MATCH($A11,'Fee Switch-Off'!$A$5:$A$30,0)) -> CHARLENE ADAMS | C11: =INDEX('Fee Switch-Off'!$E$5:$E$30,MATCH($A11,'Fee Switch-Off'!$A$5:$A$30,0)) -> 18213.8 | D11: =INDEX('Fee Switch-Off'!$G$5:$G$30,MATCH($A11,'Fee Switch-Off'!$A$5:$A$30,0)) -> 0.69 | E11: =INDEX('Fee Switch-Off'!$K$5:$K$30,MATCH($A11,'Fee Switch-Off'!$A$5:$A$30,0)) -> 0 | F11: =ROUND(C11*D11/100+1E-9,2) -> 125.68 | G11: =ROUND(C11*E11/100+1E-9,2) -> 0 | H11: =ROUND(F11/Assumptions!$B$4+1E-9,2) -> 10.47 | I11: =ROUND(G11/Assumptions!$B$4+1E-9,2) -> 0 | J11: =ROUND(H11-I11+1E-9,2) -> 10.47 | K11: 46255 | L11: =EDATE(K11,-1) -> 46224 | M11: =K11-L11 -> 31 | N11: =Assumptions!$B$6 -> 46238 | O11: =MAX(0,MIN(M11,K11-N11)) -> 17 | P11: =IF(J11>0,ROUND(J11*O11/M11+1E-9,2),0) -> 5.74 | Q11: =IF(J11<0,ROUND(-J11*O11/M11+1E-9,2),0) -> 0 | R11: 100 | S11: =ROUND(P11/Assumptions!$B$3*R11/100+1E-9,2) -> 4.99 | T11: =ROUND(I11/Assumptions!$B$3*O11/M11*R11/100+1E-9,2) -> 0 | U11: =ROUND(E11/Assumptions!$B$3*R11/100+1E-9,3) -> 0 | V11: =INDEX('Fee Switch-Off'!$F$5:$F$30,MATCH($A11,'Fee Switch-Off'!$A$5:$A$30,0)) -> 1000 | W11: =-S11 -> -4.99
A12: 113577840001 | B12: =INDEX('Fee Switch-Off'!$B$5:$B$30,MATCH($A12,'Fee Switch-Off'!$A$5:$A$30,0)) -> BONGANI MAHLANGU | C12: =INDEX('Fee Switch-Off'!$E$5:$E$30,MATCH($A12,'Fee Switch-Off'!$A$5:$A$30,0)) -> 29646.4 | D12: =INDEX('Fee Switch-Off'!$G$5:$G$30,MATCH($A12,'Fee Switch-Off'!$A$5:$A$30,0)) -> 1.035 | E12: =INDEX('Fee Switch-Off'!$K$5:$K$30,MATCH($A12,'Fee Switch-Off'!$A$5:$A$30,0)) -> 0 | F12: =ROUND(C12*D12/100+1E-9,2) -> 306.84 | G12: =ROUND(C12*E12/100+1E-9,2) -> 0 | H12: =ROUND(F12/Assumptions!$B$4+1E-9,2) -> 25.57 | I12: =ROUND(G12/Assumptions!$B$4+1E-9,2) -> 0 | J12: =ROUND(H12-I12+1E-9,2) -> 25.57 | K12: 46267 | L12: =EDATE(K12,-1) -> 46236 | M12: =K12-L12 -> 31 | N12: =Assumptions!$B$6 -> 46238 | O12: =MAX(0,MIN(M12,K12-N12)) -> 29 | P12: =IF(J12>0,ROUND(J12*O12/M12+1E-9,2),0) -> 23.92 | Q12: =IF(J12<0,ROUND(-J12*O12/M12+1E-9,2),0) -> 0 | R12: 100 | S12: =ROUND(P12/Assumptions!$B$3*R12/100+1E-9,2) -> 20.8 | T12: =ROUND(I12/Assumptions!$B$3*O12/M12*R12/100+1E-9,2) -> 0 | U12: =ROUND(E12/Assumptions!$B$3*R12/100+1E-9,3) -> 0 | V12: =INDEX('Fee Switch-Off'!$F$5:$F$30,MATCH($A12,'Fee Switch-Off'!$A$5:$A$30,0)) -> 2000 | W12: =-S12 -> -20.8
A13: 111890254001 | B13: =INDEX('Fee Switch-Off'!$B$5:$B$30,MATCH($A13,'Fee Switch-Off'!$A$5:$A$30,0)) -> FATIMA OSMAN | C13: =INDEX('Fee Switch-Off'!$E$5:$E$30,MATCH($A13,'Fee Switch-Off'!$A$5:$A$30,0)) -> 149814 | D13: =INDEX('Fee Switch-Off'!$G$5:$G$30,MATCH($A13,'Fee Switch-Off'!$A$5:$A$30,0)) -> 0.46 | E13: =INDEX('Fee Switch-Off'!$K$5:$K$30,MATCH($A13,'Fee Switch-Off'!$A$5:$A$30,0)) -> 0 | F13: =ROUND(C13*D13/100+1E-9,2) -> 689.14 | G13: =ROUND(C13*E13/100+1E-9,2) -> 0 | H13: =ROUND(F13/Assumptions!$B$4+1E-9,2) -> 57.43 | I13: =ROUND(G13/Assumptions!$B$4+1E-9,2) -> 0 | J13: =ROUND(H13-I13+1E-9,2) -> 57.43 | K13: 46248 | L13: =EDATE(K13,-1) -> 46217 | M13: =K13-L13 -> 31 | N13: =Assumptions!$B$6 -> 46238 | O13: =MAX(0,MIN(M13,K13-N13)) -> 10 | P13: =IF(J13>0,ROUND(J13*O13/M13+1E-9,2),0) -> 18.53 | Q13: =IF(J13<0,ROUND(-J13*O13/M13+1E-9,2),0) -> 0 | R13: 100 | S13: =ROUND(P13/Assumptions!$B$3*R13/100+1E-9,2) -> 16.11 | T13: =ROUND(I13/Assumptions!$B$3*O13/M13*R13/100+1E-9,2) -> 0 | U13: =ROUND(E13/Assumptions!$B$3*R13/100+1E-9,3) -> 0 | V13: =INDEX('Fee Switch-Off'!$F$5:$F$30,MATCH($A13,'Fee Switch-Off'!$A$5:$A$30,0)) -> 2800 | W13: =-S13 -> -16.11
A14: 112045877001 | B14: =INDEX('Fee Switch-Off'!$B$5:$B$30,MATCH($A14,'Fee Switch-Off'!$A$5:$A$30,0)) -> ITUMELENG SELLO | C14: =INDEX('Fee Switch-Off'!$E$5:$E$30,MATCH($A14,'Fee Switch-Off'!$A$5:$A$30,0)) -> 88935.84 | D14: =INDEX('Fee Switch-Off'!$G$5:$G$30,MATCH($A14,'Fee Switch-Off'!$A$5:$A$30,0)) -> 0.92 | E14: =INDEX('Fee Switch-Off'!$K$5:$K$30,MATCH($A14,'Fee Switch-Off'!$A$5:$A$30,0)) -> 0 | F14: =ROUND(C14*D14/100+1E-9,2) -> 818.21 | G14: =ROUND(C14*E14/100+1E-9,2) -> 0 | H14: =ROUND(F14/Assumptions!$B$4+1E-9,2) -> 68.18 | I14: =ROUND(G14/Assumptions!$B$4+1E-9,2) -> 0 | J14: =ROUND(H14-I14+1E-9,2) -> 68.18 | K14: 46240 | L14: =EDATE(K14,-1) -> 46209 | M14: =K14-L14 -> 31 | N14: =Assumptions!$B$6 -> 46238 | O14: =MAX(0,MIN(M14,K14-N14)) -> 2 | P14: =IF(J14>0,ROUND(J14*O14/M14+1E-9,2),0) -> 4.4 | Q14: =IF(J14<0,ROUND(-J14*O14/M14+1E-9,2),0) -> 0 | R14: 100 | S14: =ROUND(P14/Assumptions!$B$3*R14/100+1E-9,2) -> 3.83 | T14: =ROUND(I14/Assumptions!$B$3*O14/M14*R14/100+1E-9,2) -> 0 | U14: =ROUND(E14/Assumptions!$B$3*R14/100+1E-9,3) -> 0 | V14: =INDEX('Fee Switch-Off'!$F$5:$F$30,MATCH($A14,'Fee Switch-Off'!$A$5:$A$30,0)) -> 1800 | W14: =-S14 -> -3.83
A15: 112476310001 | B15: =INDEX('Fee Switch-Off'!$B$5:$B$30,MATCH($A15,'Fee Switch-Off'!$A$5:$A$30,0)) -> CHANTEL VAN WYK | C15: =INDEX('Fee Switch-Off'!$E$5:$E$30,MATCH($A15,'Fee Switch-Off'!$A$5:$A$30,0)) -> 140507.5 | D15: =INDEX('Fee Switch-Off'!$G$5:$G$30,MATCH($A15,'Fee Switch-Off'!$A$5:$A$30,0)) -> 1.725 | E15: =INDEX('Fee Switch-Off'!$K$5:$K$30,MATCH($A15,'Fee Switch-Off'!$A$5:$A$30,0)) -> 0 | F15: =ROUND(C15*D15/100+1E-9,2) -> 2423.75 | G15: =ROUND(C15*E15/100+1E-9,2) -> 0 | H15: =ROUND(F15/Assumptions!$B$4+1E-9,2) -> 201.98 | I15: =ROUND(G15/Assumptions!$B$4+1E-9,2) -> 0 | J15: =ROUND(H15-I15+1E-9,2) -> 201.98 | K15: 46261 | L15: =EDATE(K15,-1) -> 46230 | M15: =K15-L15 -> 31 | N15: =Assumptions!$B$6 -> 46238 | O15: =MAX(0,MIN(M15,K15-N15)) -> 23 | P15: =IF(J15>0,ROUND(J15*O15/M15+1E-9,2),0) -> 149.86 | Q15: =IF(J15<0,ROUND(-J15*O15/M15+1E-9,2),0) -> 0 | R15: 100 | S15: =ROUND(P15/Assumptions!$B$3*R15/100+1E-9,2) -> 130.31 | T15: =ROUND(I15/Assumptions!$B$3*O15/M15*R15/100+1E-9,2) -> 0 | U15: =ROUND(E15/Assumptions!$B$3*R15/100+1E-9,3) -> 0 | V15: =INDEX('Fee Switch-Off'!$F$5:$F$30,MATCH($A15,'Fee Switch-Off'!$A$5:$A$30,0)) -> 3500 | W15: =-S15 -> -130.31
A16: 112718459001 | B16: =INDEX('Fee Switch-Off'!$B$5:$B$30,MATCH($A16,'Fee Switch-Off'!$A$5:$A$30,0)) -> MPHO DLAMINI | C16: =INDEX('Fee Switch-Off'!$E$5:$E$30,MATCH($A16,'Fee Switch-Off'!$A$5:$A$30,0)) -> 21021.72 | D16: =INDEX('Fee Switch-Off'!$G$5:$G$30,MATCH($A16,'Fee Switch-Off'!$A$5:$A$30,0)) -> 0.345 | E16: =INDEX('Fee Switch-Off'!$K$5:$K$30,MATCH($A16,'Fee Switch-Off'!$A$5:$A$30,0)) -> 0 | F16: =ROUND(C16*D16/100+1E-9,2) -> 72.52 | G16: =ROUND(C16*E16/100+1E-9,2) -> 0 | H16: =ROUND(F16/Assumptions!$B$4+1E-9,2) -> 6.04 | I16: =ROUND(G16/Assumptions!$B$4+1E-9,2) -> 0 | J16: =ROUND(H16-I16+1E-9,2) -> 6.04 | K16: 46249 | L16: =EDATE(K16,-1) -> 46218 | M16: =K16-L16 -> 31 | N16: =Assumptions!$B$6 -> 46238 | O16: =MAX(0,MIN(M16,K16-N16)) -> 11 | P16: =IF(J16>0,ROUND(J16*O16/M16+1E-9,2),0) -> 2.14 | Q16: =IF(J16<0,ROUND(-J16*O16/M16+1E-9,2),0) -> 0 | R16: 100 | S16: =ROUND(P16/Assumptions!$B$3*R16/100+1E-9,2) -> 1.86 | T16: =ROUND(I16/Assumptions!$B$3*O16/M16*R16/100+1E-9,2) -> 0 | U16: =ROUND(E16/Assumptions!$B$3*R16/100+1E-9,3) -> 0 | V16: =INDEX('Fee Switch-Off'!$F$5:$F$30,MATCH($A16,'Fee Switch-Off'!$A$5:$A$30,0)) -> 600 | W16: =-S16 -> -1.86
... A30: 114723506001 | B30: =INDEX('Fee Switch-Off'!$B$5:$B$30,MATCH($A30,'Fee Switch-Off'!$A$5:$A$30,0)) -> RUBEN PILLAY | C30: =INDEX('Fee Switch-Off'!$E$5:$E$30,MATCH($A30,'Fee Switch-Off'!$A$5:$A$30,0)) -> 17293.92 | D30: =INDEX('Fee Switch-Off'!$G$5:$G$30,MATCH($A30,'Fee Switch-Off'!$A$5:$A$30,0)) -> 1.15 | E30: =INDEX('Fee Switch-Off'!$K$5:$K$30,MATCH($A30,'Fee Switch-Off'!$A$5:$A$30,0)) -> 0 | F30: =ROUND(C30*D30/100+1E-9,2) -> 198.88 | G30: =ROUND(C30*E30/100+1E-9,2) -> 0 | H30: =ROUND(F30/Assumptions!$B$4+1E-9,2) -> 16.57 | I30: =ROUND(G30/Assumptions!$B$4+1E-9,2) -> 0 | J30: =ROUND(H30-I30+1E-9,2) -> 16.57 | K30: 46263 | L30: =EDATE(K30,-1) -> 46232 | M30: =K30-L30 -> 31 | N30: =Assumptions!$B$6 -> 46238 | O30: =MAX(0,MIN(M30,K30-N30)) -> 25 | P30: =IF(J30>0,ROUND(J30*O30/M30+1E-9,2),0) -> 13.36 | Q30: =IF(J30<0,ROUND(-J30*O30/M30+1E-9,2),0) -> 0 | R30: 100 | S30: =ROUND(P30/Assumptions!$B$3*R30/100+1E-9,2) -> 11.62 | T30: =ROUND(I30/Assumptions!$B$3*O30/M30*R30/100+1E-9,2) -> 0 | U30: =ROUND(E30/Assumptions!$B$3*R30/100+1E-9,3) -> 0 | V30: =INDEX('Fee Switch-Off'!$F$5:$F$30,MATCH($A30,'Fee Switch-Off'!$A$5:$A$30,0)) -> 2400 | W30: =-S30 -> -11.62

Sheet EAC
A1: EAC: the Effective Annual Cost at the four milestones on Endr Quote Summary
A2: Monthly contributions are projected at the fund's gross growth with and without charges; EAC is the gap between the two annualised returns (Excel FV and RATE, annuity-due). Charges interact slightly, so each component is measured alone and scaled so the components add up to the total.
A4: Contract No. | B4: Milestone | C4: Years | D4: Term (months) | E4: Months to milestone | F4: Monthly contribution (R) | G4: Gross growth (% a year) | H4: Fund charge (%) | I4: Advice fee after, VAT incl (%) | J4: Admin charge (%) | K4: Initial charge (%) | L4: Other (%) | M4: All: net growth | N4: All: final value (R) | O4: All: IRR | P4: All: EAC (pts) | Q4: Fund: net growth | R4: Fund: final value (R) | S4: Fund: IRR | T4: Fund: EAC (pts) | U4: Advice: net growth | V4: Advice: final value (R) | W4: Advice: IRR | X4: Advice: EAC (pts) | Y4: Admin: net growth | Z4: Admin: final value (R) | AA4: Admin: IRR | AB4: Admin: EAC (pts) | AC4: Sum of components | AD4: Investment | AE4: Advice | AF4: Admin | AG4: Other | AH4: EAC
A5: 119900001001 | B5: 1 | C5: =IF(ROUND(D5/12,0)>10,CHOOSE(B5,1,5,10,ROUND(D5/12,0)),CHOOSE(B5,1,3,5,ROUND(D5/12,0))) -> 1 | D5: 240 | E5: =C5*12 -> 12 | F5: =INDEX('Fee Switch-Off'!$F$5:$F$30,MATCH($A5,'Fee Switch-Off'!$A$5:$A$30,0)) -> 600 | G5: 8.6 | H5: =IF(ISNUMBER(SEARCH("TFI",INDEX('Fee Switch-Off'!$C$5:$C$30,MATCH($A5,'Fee Switch-Off'!$A$5:$A$30,0)))),Assumptions!$B$8,Assumptions!$B$7) -> 0.85 | I5: =INDEX('Quote Summary'!$E$5:$E$30,MATCH($A5,'Quote Summary'!$A$5:$A$30,0)) -> 0 | J5: =Assumptions!$B$9 -> 0.35 | K5: =Assumptions!$B$10 -> 1.725 | L5: =Assumptions!$B$11 -> 0 | M5: =(G5-(H5+J5+I5+L5))/100 -> 0.074 | N5: =F5*(1-(K5)/100)*(((1+M5)^(E5/12)-1)/((1+M5)^(1/12)-1))*(1+M5)^(1/12) -> 7356.3285 | O5: =(1+RATE(E5,-F5,0,N5,1))^12-1 -> 0.040327815 | P5: =(G5/100-O5)*100 -> 4.5672185 | Q5: =(G5-(H5))/100 -> 0.0775 | R5: =F5*(1-(0)/100)*(((1+Q5)^(E5/12)-1)/((1+Q5)^(1/12)-1))*(1+Q5)^(1/12) -> 7498.8035 | S5: =(1+RATE(E5,-F5,0,R5,1))^12-1 -> 0.0775 | T5: =(G5/100-S5)*100 -> 0.85 | U5: =(G5-(I5))/100 -> 0.086 | V5: =F5*(1-(0)/100)*(((1+U5)^(E5/12)-1)/((1+U5)^(1/12)-1))*(1+U5)^(1/12) -> 7531.173 | W5: =(1+RATE(E5,-F5,0,V5,1))^12-1 -> 0.086 | X5: =(G5/100-W5)*100 -> -5.2735594e-14 | Y5: =(G5-(J5))/100 -> 0.0825 | Z5: =F5*(1-(K5)/100)*(((1+Y5)^(E5/12)-1)/((1+Y5)^(1/12)-1))*(1+Y5)^(1/12) -> 7388.1707 | AA5: =(1+RATE(E5,-F5,0,Z5,1))^12-1 -> 0.048601253 | AB5: =(G5/100-AA5)*100 -> 3.7398747 | AC5: =T5+X5+AB5 -> 4.5898747 | AD5: =IF(AC5=0,0,ROUND(T5*P5/AC5+1E-9,2)) -> 0.85 | AE5: =IF(AC5=0,0,ROUND(X5*P5/AC5+1E-9,2)) -> 0 | AF5: =IF(AC5=0,0,ROUND(AB5*P5/AC5+1E-9,2)) -> 3.72 | AG5: 0 | AH5: =ROUND(AD5+AE5+AF5+AG5+1E-9,2) -> 4.57
A6: 119900001001 | B6: 2 | C6: =IF(ROUND(D6/12,0)>10,CHOOSE(B6,1,5,10,ROUND(D6/12,0)),CHOOSE(B6,1,3,5,ROUND(D6/12,0))) -> 5 | D6: 240 | E6: =C6*12 -> 60 | F6: =INDEX('Fee Switch-Off'!$F$5:$F$30,MATCH($A6,'Fee Switch-Off'!$A$5:$A$30,0)) -> 600 | G6: 8.6 | H6: =IF(ISNUMBER(SEARCH("TFI",INDEX('Fee Switch-Off'!$C$5:$C$30,MATCH($A6,'Fee Switch-Off'!$A$5:$A$30,0)))),Assumptions!$B$8,Assumptions!$B$7) -> 0.85 | I6: =INDEX('Quote Summary'!$E$5:$E$30,MATCH($A6,'Quote Summary'!$A$5:$A$30,0)) -> 0 | J6: =Assumptions!$B$9 -> 0.35 | K6: =Assumptions!$B$10 -> 1.725 | L6: =Assumptions!$B$11 -> 0 | M6: =(G6-(H6+J6+I6+L6))/100 -> 0.074 | N6: =F6*(1-(K6)/100)*(((1+M6)^(E6/12)-1)/((1+M6)^(1/12)-1))*(1+M6)^(1/12) -> 42643.284 | O6: =(1+RATE(E6,-F6,0,N6,1))^12-1 -> 0.067057987 | P6: =(G6/100-O6)*100 -> 1.8942013 | Q6: =(G6-(H6))/100 -> 0.0775 | R6: =F6*(1-(0)/100)*(((1+Q6)^(E6/12)-1)/((1+Q6)^(1/12)-1))*(1+Q6)^(1/12) -> 43773.711 | S6: =(1+RATE(E6,-F6,0,R6,1))^12-1 -> 0.0775 | T6: =(G6/100-S6)*100 -> 0.85 | U6: =(G6-(I6))/100 -> 0.086 | V6: =F6*(1-(0)/100)*(((1+U6)^(E6/12)-1)/((1+U6)^(1/12)-1))*(1+U6)^(1/12) -> 44714.042 | W6: =(1+RATE(E6,-F6,0,V6,1))^12-1 -> 0.086 | X6: =(G6/100-W6)*100 -> -5.2735594e-14 | Y6: =(G6-(J6))/100 -> 0.0825 | Z6: =F6*(1-(K6)/100)*(((1+Y6)^(E6/12)-1)/((1+Y6)^(1/12)-1))*(1+Y6)^(1/12) -> 43560.037 | AA6: =(1+RATE(E6,-F6,0,Z6,1))^12-1 -> 0.075545293 | AB6: =(G6/100-AA6)*100 -> 1.0454707 | AC6: =T6+X6+AB6 -> 1.8954707 | AD6: =IF(AC6=0,0,ROUND(T6*P6/AC6+1E-9,2)) -> 0.85 | AE6: =IF(AC6=0,0,ROUND(X6*P6/AC6+1E-9,2)) -> 0 | AF6: =IF(AC6=0,0,ROUND(AB6*P6/AC6+1E-9,2)) -> 1.04 | AG6: 0 | AH6: =ROUND(AD6+AE6+AF6+AG6+1E-9,2) -> 1.89
A7: 119900001001 | B7: 3 | C7: =IF(ROUND(D7/12,0)>10,CHOOSE(B7,1,5,10,ROUND(D7/12,0)),CHOOSE(B7,1,3,5,ROUND(D7/12,0))) -> 10 | D7: 240 | E7: =C7*12 -> 120 | F7: =INDEX('Fee Switch-Off'!$F$5:$F$30,MATCH($A7,'Fee Switch-Off'!$A$5:$A$30,0)) -> 600 | G7: 8.6 | H7: =IF(ISNUMBER(SEARCH("TFI",INDEX('Fee Switch-Off'!$C$5:$C$30,MATCH($A7,'Fee Switch-Off'!$A$5:$A$30,0)))),Assumptions!$B$8,Assumptions!$B$7) -> 0.85 | I7: =INDEX('Quote Summary'!$E$5:$E$30,MATCH($A7,'Quote Summary'!$A$5:$A$30,0)) -> 0 | J7: =Assumptions!$B$9 -> 0.35 | K7: =Assumptions!$B$10 -> 1.725 | L7: =Assumptions!$B$11 -> 0 | M7: =(G7-(H7+J7+I7+L7))/100 -> 0.074 | N7: =F7*(1-(K7)/100)*(((1+M7)^(E7/12)-1)/((1+M7)^(1/12)-1))*(1+M7)^(1/12) -> 103579.02 | O7: =(1+RATE(E7,-F7,0,N7,1))^12-1 -> 0.070679235 | P7: =(G7/100-O7)*100 -> 1.5320765 | Q7: =(G7-(H7))/100 -> 0.0775 | R7: =F7*(1-(0)/100)*(((1+Q7)^(E7/12)-1)/((1+Q7)^(1/12)-1))*(1+Q7)^(1/12) -> 107350.67 | S7: =(1+RATE(E7,-F7,0,R7,1))^12-1 -> 0.0775 | T7: =(G7/100-S7)*100 -> 0.85 | U7: =(G7-(I7))/100 -> 0.086 | V7: =F7*(1-(0)/100)*(((1+U7)^(E7/12)-1)/((1+U7)^(1/12)-1))*(1+U7)^(1/12) -> 112259.02 | W7: =(1+RATE(E7,-F7,0,V7,1))^12-1 -> 0.086 | X7: =(G7/100-W7)*100 -> -5.2735594e-14 | Y7: =(G7-(J7))/100 -> 0.0825 | Z7: =F7*(1-(K7)/100)*(((1+Y7)^(E7/12)-1)/((1+Y7)^(1/12)-1))*(1+Y7)^(1/12) -> 108308.25 | AA7: =(1+RATE(E7,-F7,0,Z7,1))^12-1 -> 0.079190635 | AB7: =(G7/100-AA7)*100 -> 0.68093655 | AC7: =T7+X7+AB7 -> 1.5309365 | AD7: =IF(AC7=0,0,ROUND(T7*P7/AC7+1E-9,2)) -> 0.85 | AE7: =IF(AC7=0,0,ROUND(X7*P7/AC7+1E-9,2)) -> 0 | AF7: =IF(AC7=0,0,ROUND(AB7*P7/AC7+1E-9,2)) -> 0.68 | AG7: 0 | AH7: =ROUND(AD7+AE7+AF7+AG7+1E-9,2) -> 1.53
A8: 119900001001 | B8: 4 | C8: =IF(ROUND(D8/12,0)>10,CHOOSE(B8,1,5,10,ROUND(D8/12,0)),CHOOSE(B8,1,3,5,ROUND(D8/12,0))) -> 20 | D8: 240 | E8: =C8*12 -> 240 | F8: =INDEX('Fee Switch-Off'!$F$5:$F$30,MATCH($A8,'Fee Switch-Off'!$A$5:$A$30,0)) -> 600 | G8: 8.6 | H8: =IF(ISNUMBER(SEARCH("TFI",INDEX('Fee Switch-Off'!$C$5:$C$30,MATCH($A8,'Fee Switch-Off'!$A$5:$A$30,0)))),Assumptions!$B$8,Assumptions!$B$7) -> 0.85 | I8: =INDEX('Quote Summary'!$E$5:$E$30,MATCH($A8,'Quote Summary'!$A$5:$A$30,0)) -> 0 | J8: =Assumptions!$B$9 -> 0.35 | K8: =Assumptions!$B$10 -> 1.725 | L8: =Assumptions!$B$11 -> 0 | M8: =(G8-(H8+J8+I8+L8))/100 -> 0.074 | N8: =F8*(1-(K8)/100)*(((1+M8)^(E8/12)-1)/((1+M8)^(1/12)-1))*(1+M8)^(1/12) -> 315081.08 | O8: =(1+RATE(E8,-F8,0,N8,1))^12-1 -> 0.072484523 | P8: =(G8/100-O8)*100 -> 1.3515477 | Q8: =(G8-(H8))/100 -> 0.0775 | R8: =F8*(1-(0)/100)*(((1+Q8)^(E8/12)-1)/((1+Q8)^(1/12)-1))*(1+Q8)^(1/12) -> 333803.39 | S8: =(1+RATE(E8,-F8,0,R8,1))^12-1 -> 0.0775 | T8: =(G8/100-S8)*100 -> 0.85 | U8: =(G8-(I8))/100 -> 0.086 | V8: =F8*(1-(0)/100)*(((1+U8)^(E8/12)-1)/((1+U8)^(1/12)-1))*(1+U8)^(1/12) -> 368423.85 | W8: =(1+RATE(E8,-F8,0,V8,1))^12-1 -> 0.086 | X8: =(G8/100-W8)*100 -> -5.2735594e-14 | Y8: =(G8-(J8))/100 -> 0.0825 | Z8: =F8*(1-(K8)/100)*(((1+Y8)^(E8/12)-1)/((1+Y8)^(1/12)-1))*(1+Y8)^(1/12) -> 347607.07 | AA8: =(1+RATE(E8,-F8,0,Z8,1))^12-1 -> 0.081001246 | AB8: =(G8/100-AA8)*100 -> 0.49987542 | AC8: =T8+X8+AB8 -> 1.3498754 | AD8: =IF(AC8=0,0,ROUND(T8*P8/AC8+1E-9,2)) -> 0.85 | AE8: =IF(AC8=0,0,ROUND(X8*P8/AC8+1E-9,2)) -> 0 | AF8: =IF(AC8=0,0,ROUND(AB8*P8/AC8+1E-9,2)) -> 0.5 | AG8: 0 | AH8: =ROUND(AD8+AE8+AF8+AG8+1E-9,2) -> 1.35
A9: 110671307001 | B9: 1 | C9: =IF(ROUND(D9/12,0)>10,CHOOSE(B9,1,5,10,ROUND(D9/12,0)),CHOOSE(B9,1,3,5,ROUND(D9/12,0))) -> 1 | D9: 240 | E9: =C9*12 -> 12 | F9: =INDEX('Fee Switch-Off'!$F$5:$F$30,MATCH($A9,'Fee Switch-Off'!$A$5:$A$30,0)) -> 2500 | G9: 9.05 | H9: =IF(ISNUMBER(SEARCH("TFI",INDEX('Fee Switch-Off'!$C$5:$C$30,MATCH($A9,'Fee Switch-Off'!$A$5:$A$30,0)))),Assumptions!$B$8,Assumptions!$B$7) -> 0.7 | I9: =INDEX('Quote Summary'!$E$5:$E$30,MATCH($A9,'Quote Summary'!$A$5:$A$30,0)) -> 0 | J9: =Assumptions!$B$9 -> 0.35 | K9: =Assumptions!$B$10 -> 1.725 | L9: =Assumptions!$B$11 -> 0 | M9: =(G9-(H9+J9+I9+L9))/100 -> 0.08 | N9: =F9*(1-(K9)/100)*(((1+M9)^(E9/12)-1)/((1+M9)^(1/12)-1))*(1+M9)^(1/12) -> 30745.055 | O9: =(1+RATE(E9,-F9,0,N9,1))^12-1 -> 0.046167866 | P9: =(G9/100-O9)*100 -> 4.4332134 | Q9: =(G9-(H9))/100 -> 0.0835 | R9: =F9*(1-(0)/100)*(((1+Q9)^(E9/12)-1)/((1+Q9)^(1/12)-1))*(1+Q9)^(1/12) -> 31340.252 | S9: =(1+RATE(E9,-F9,0,R9,1))^12-1 -> 0.0835 | T9: =(G9/100-S9)*100 -> 0.7 | U9: =(G9-(I9))/100 -> 0.0905 | V9: =F9*(1-(0)/100)*(((1+U9)^(E9/12)-1)/((1+U9)^(1/12)-1))*(1+U9)^(1/12) -> 31451.162 | W9: =(1+RATE(E9,-F9,0,V9,1))^12-1 -> 0.0905 | X9: =(G9/100-W9)*100 -> 4.2049697e-13 | Y9: =(G9-(J9))/100 -> 0.087 | Z9: =F9*(1-(K9)/100)*(((1+Y9)^(E9/12)-1)/((1+Y9)^(1/12)-1))*(1+Y9)^(1/12) -> 30854.157 | AA9: =(1+RATE(E9,-F9,0,Z9,1))^12-1 -> 0.052981396 | AB9: =(G9/100-AA9)*100 -> 3.7518604 | AC9: =T9+X9+AB9 -> 4.4518604 | AD9: =IF(AC9=0,0,ROUND(T9*P9/AC9+1E-9,2)) -> 0.7 | AE9: =IF(AC9=0,0,ROUND(X9*P9/AC9+1E-9,2)) -> 0 | AF9: =IF(AC9=0,0,ROUND(AB9*P9/AC9+1E-9,2)) -> 3.74 | AG9: 0 | AH9: =ROUND(AD9+AE9+AF9+AG9+1E-9,2) -> 4.44
A10: 110671307001 | B10: 2 | C10: =IF(ROUND(D10/12,0)>10,CHOOSE(B10,1,5,10,ROUND(D10/12,0)),CHOOSE(B10,1,3,5,ROUND(D10/12,0))) -> 5 | D10: 240 | E10: =C10*12 -> 60 | F10: =INDEX('Fee Switch-Off'!$F$5:$F$30,MATCH($A10,'Fee Switch-Off'!$A$5:$A$30,0)) -> 2500 | G10: 9.05 | H10: =IF(ISNUMBER(SEARCH("TFI",INDEX('Fee Switch-Off'!$C$5:$C$30,MATCH($A10,'Fee Switch-Off'!$A$5:$A$30,0)))),Assumptions!$B$8,Assumptions!$B$7) -> 0.7 | I10: =INDEX('Quote Summary'!$E$5:$E$30,MATCH($A10,'Quote Summary'!$A$5:$A$30,0)) -> 0 | J10: =Assumptions!$B$9 -> 0.35 | K10: =Assumptions!$B$10 -> 1.725 | L10: =Assumptions!$B$11 -> 0 | M10: =(G10-(H10+J10+I10+L10))/100 -> 0.08 | N10: =F10*(1-(K10)/100)*(((1+M10)^(E10/12)-1)/((1+M10)^(1/12)-1))*(1+M10)^(1/12) -> 180368.97 | O10: =(1+RATE(E10,-F10,0,N10,1))^12-1 -> 0.073049051 | P10: =(G10/100-O10)*100 -> 1.7450949 | Q10: =(G10-(H10))/100 -> 0.0835 | R10: =F10*(1-(0)/100)*(((1+Q10)^(E10/12)-1)/((1+Q10)^(1/12)-1))*(1+Q10)^(1/12) -> 185148.24 | S10: =(1+RATE(E10,-F10,0,R10,1))^12-1 -> 0.0835 | T10: =(G10/100-S10)*100 -> 0.7 | U10: =(G10-(I10))/100 -> 0.0905 | V10: =F10*(1-(0)/100)*(((1+U10)^(E10/12)-1)/((1+U10)^(1/12)-1))*(1+U10)^(1/12) -> 188413.71 | W10: =(1+RATE(E10,-F10,0,V10,1))^12-1 -> 0.0905 | X10: =(G10/100-W10)*100 -> 4.2049697e-13 | Y10: =(G10-(J10))/100 -> 0.087 | Z10: =F10*(1-(K10)/100)*(((1+Y10)^(E10/12)-1)/((1+Y10)^(1/12)-1))*(1+Y10)^(1/12) -> 183552.61 | AA10: =(1+RATE(E10,-F10,0,Z10,1))^12-1 -> 0.080038475 | AB10: =(G10/100-AA10)*100 -> 1.0461525 | AC10: =T10+X10+AB10 -> 1.7461525 | AD10: =IF(AC10=0,0,ROUND(T10*P10/AC10+1E-9,2)) -> 0.7 | AE10: =IF(AC10=0,0,ROUND(X10*P10/AC10+1E-9,2)) -> 0 | AF10: =IF(AC10=0,0,ROUND(AB10*P10/AC10+1E-9,2)) -> 1.05 | AG10: 0 | AH10: =ROUND(AD10+AE10+AF10+AG10+1E-9,2) -> 1.75
A11: 110671307001 | B11: 3 | C11: =IF(ROUND(D11/12,0)>10,CHOOSE(B11,1,5,10,ROUND(D11/12,0)),CHOOSE(B11,1,3,5,ROUND(D11/12,0))) -> 10 | D11: 240 | E11: =C11*12 -> 120 | F11: =INDEX('Fee Switch-Off'!$F$5:$F$30,MATCH($A11,'Fee Switch-Off'!$A$5:$A$30,0)) -> 2500 | G11: 9.05 | H11: =IF(ISNUMBER(SEARCH("TFI",INDEX('Fee Switch-Off'!$C$5:$C$30,MATCH($A11,'Fee Switch-Off'!$A$5:$A$30,0)))),Assumptions!$B$8,Assumptions!$B$7) -> 0.7 | I11: =INDEX('Quote Summary'!$E$5:$E$30,MATCH($A11,'Quote Summary'!$A$5:$A$30,0)) -> 0 | J11: =Assumptions!$B$9 -> 0.35 | K11: =Assumptions!$B$10 -> 1.725 | L11: =Assumptions!$B$11 -> 0 | M11: =(G11-(H11+J11+I11+L11))/100 -> 0.08 | N11: =F11*(1-(K11)/100)*(((1+M11)^(E11/12)-1)/((1+M11)^(1/12)-1))*(1+M11)^(1/12) -> 445390.16 | O11: =(1+RATE(E11,-F11,0,N11,1))^12-1 -> 0.076687362 | P11: =(G11/100-O11)*100 -> 1.3812638 | Q11: =(G11-(H11))/100 -> 0.0835 | R11: =F11*(1-(0)/100)*(((1+Q11)^(E11/12)-1)/((1+Q11)^(1/12)-1))*(1+Q11)^(1/12) -> 461628.53 | S11: =(1+RATE(E11,-F11,0,R11,1))^12-1 -> 0.0835 | T11: =(G11/100-S11)*100 -> 0.7 | U11: =(G11-(I11))/100 -> 0.0905 | V11: =F11*(1-(0)/100)*(((1+U11)^(E11/12)-1)/((1+U11)^(1/12)-1))*(1+U11)^(1/12) -> 478977.08 | W11: =(1+RATE(E11,-F11,0,V11,1))^12-1 -> 0.0905 | X11: =(G11/100-W11)*100 -> 4.2049697e-13 | Y11: =(G11-(J11))/100 -> 0.087 | Z11: =F11*(1-(K11)/100)*(((1+Y11)^(E11/12)-1)/((1+Y11)^(1/12)-1))*(1+Y11)^(1/12) -> 462105.9 | AA11: =(1+RATE(E11,-F11,0,Z11,1))^12-1 -> 0.08369636 | AB11: =(G11/100-AA11)*100 -> 0.680364 | AC11: =T11+X11+AB11 -> 1.380364 | AD11: =IF(AC11=0,0,ROUND(T11*P11/AC11+1E-9,2)) -> 0.7 | AE11: =IF(AC11=0,0,ROUND(X11*P11/AC11+1E-9,2)) -> 0 | AF11: =IF(AC11=0,0,ROUND(AB11*P11/AC11+1E-9,2)) -> 0.68 | AG11: 0 | AH11: =ROUND(AD11+AE11+AF11+AG11+1E-9,2) -> 1.38
A12: 110671307001 | B12: 4 | C12: =IF(ROUND(D12/12,0)>10,CHOOSE(B12,1,5,10,ROUND(D12/12,0)),CHOOSE(B12,1,3,5,ROUND(D12/12,0))) -> 20 | D12: 240 | E12: =C12*12 -> 240 | F12: =INDEX('Fee Switch-Off'!$F$5:$F$30,MATCH($A12,'Fee Switch-Off'!$A$5:$A$30,0)) -> 2500 | G12: 9.05 | H12: =IF(ISNUMBER(SEARCH("TFI",INDEX('Fee Switch-Off'!$C$5:$C$30,MATCH($A12,'Fee Switch-Off'!$A$5:$A$30,0)))),Assumptions!$B$8,Assumptions!$B$7) -> 0.7 | I12: =INDEX('Quote Summary'!$E$5:$E$30,MATCH($A12,'Quote Summary'!$A$5:$A$30,0)) -> 0 | J12: =Assumptions!$B$9 -> 0.35 | K12: =Assumptions!$B$10 -> 1.725 | L12: =Assumptions!$B$11 -> 0 | M12: =(G12-(H12+J12+I12+L12))/100 -> 0.08 | N12: =F12*(1-(K12)/100)*(((1+M12)^(E12/12)-1)/((1+M12)^(1/12)-1))*(1+M12)^(1/12) -> 1406954.1 | O12: =(1+RATE(E12,-F12,0,N12,1))^12-1 -> 0.078496482 | P12: =(G12/100-O12)*100 -> 1.2003518 | Q12: =(G12-(H12))/100 -> 0.0835 | R12: =F12*(1-(0)/100)*(((1+Q12)^(E12/12)-1)/((1+Q12)^(1/12)-1))*(1+Q12)^(1/12) -> 1491022.9 | S12: =(1+RATE(E12,-F12,0,R12,1))^12-1 -> 0.0835 | T12: =(G12/100-S12)*100 -> 0.7 | U12: =(G12-(I12))/100 -> 0.0905 | V12: =F12*(1-(0)/100)*(((1+U12)^(E12/12)-1)/((1+U12)^(1/12)-1))*(1+U12)^(1/12) -> 1618102.2 | W12: =(1+RATE(E12,-F12,0,V12,1))^12-1 -> 0.0905 | X12: =(G12/100-W12)*100 -> 4.2049697e-13 | Y12: =(G12-(J12))/100 -> 0.087 | Z12: =F12*(1-(K12)/100)*(((1+Y12)^(E12/12)-1)/((1+Y12)^(1/12)-1))*(1+Y12)^(1/12) -> 1526339.5 | AA12: =(1+RATE(E12,-F12,0,Z12,1))^12-1 -> 0.085509506 | AB12: =(G12/100-AA12)*100 -> 0.49904943 | AC12: =T12+X12+AB12 -> 1.1990494 | AD12: =IF(AC12=0,0,ROUND(T12*P12/AC12+1E-9,2)) -> 0.7 | AE12: =IF(AC12=0,0,ROUND(X12*P12/AC12+1E-9,2)) -> 0 | AF12: =IF(AC12=0,0,ROUND(AB12*P12/AC12+1E-9,2)) -> 0.5 | AG12: 0 | AH12: =ROUND(AD12+AE12+AF12+AG12+1E-9,2) -> 1.2
A13: 112333103001 | B13: 1 | C13: =IF(ROUND(D13/12,0)>10,CHOOSE(B13,1,5,10,ROUND(D13/12,0)),CHOOSE(B13,1,3,5,ROUND(D13/12,0))) -> 1 | D13: 180 | E13: =C13*12 -> 12 | F13: =INDEX('Fee Switch-Off'!$F$5:$F$30,MATCH($A13,'Fee Switch-Off'!$A$5:$A$30,0)) -> 1200 | G13: 9.5 | H13: =IF(ISNUMBER(SEARCH("TFI",INDEX('Fee Switch-Off'!$C$5:$C$30,MATCH($A13,'Fee Switch-Off'!$A$5:$A$30,0)))),Assumptions!$B$8,Assumptions!$B$7) -> 0.85 | I13: =INDEX('Quote Summary'!$E$5:$E$30,MATCH($A13,'Quote Summary'!$A$5:$A$30,0)) -> 0 | J13: =Assumptions!$B$9 -> 0.35 | K13: =Assumptions!$B$10 -> 1.725 | L13: =Assumptions!$B$11 -> 0 | M13: =(G13-(H13+J13+I13+L13))/100 -> 0.083 | N13: =F13*(1-(K13)/100)*(((1+M13)^(E13/12)-1)/((1+M13)^(1/12)-1))*(1+M13)^(1/12) -> 14780.083 | O13: =(1+RATE(E13,-F13,0,N13,1))^12-1 -> 0.049087933 | P13: =(G13/100-O13)*100 -> 4.5912067 | Q13: =(G13-(H13))/100 -> 0.0865 | R13: =F13*(1-(0)/100)*(((1+Q13)^(E13/12)-1)/((1+Q13)^(1/12)-1))*(1+Q13)^(1/12) -> 15066.149 | S13: =(1+RATE(E13,-F13,0,R13,1))^12-1 -> 0.0865 | T13: =(G13/100-S13)*100 -> 0.85 | U13: =(G13-(I13))/100 -> 0.095 | V13: =F13*(1-(0)/100)*(((1+U13)^(E13/12)-1)/((1+U13)^(1/12)-1))*(1+U13)^(1/12) -> 15130.727 | W13: =(1+RATE(E13,-F13,0,V13,1))^12-1 -> 0.095 | X13: =(G13/100-W13)*100 -> 9.15934e-14 | Y13: =(G13-(J13))/100 -> 0.0915 | Z13: =F13*(1-(K13)/100)*(((1+Y13)^(E13/12)-1)/((1+Y13)^(1/12)-1))*(1+Y13)^(1/12) -> 14843.608 | AA13: =(1+RATE(E13,-F13,0,Z13,1))^12-1 -> 0.0573616 | AB13: =(G13/100-AA13)*100 -> 3.76384 | AC13: =T13+X13+AB13 -> 4.61384 | AD13: =IF(AC13=0,0,ROUND(T13*P13/AC13+1E-9,2)) -> 0.85 | AE13: =IF(AC13=0,0,ROUND(X13*P13/AC13+1E-9,2)) -> 0 | AF13: =IF(AC13=0,0,ROUND(AB13*P13/AC13+1E-9,2)) -> 3.75 | AG13: 0 | AH13: =ROUND(AD13+AE13+AF13+AG13+1E-9,2) -> 4.6
A14: 112333103001 | B14: 2 | C14: =IF(ROUND(D14/12,0)>10,CHOOSE(B14,1,5,10,ROUND(D14/12,0)),CHOOSE(B14,1,3,5,ROUND(D14/12,0))) -> 5 | D14: 180 | E14: =C14*12 -> 60 | F14: =INDEX('Fee Switch-Off'!$F$5:$F$30,MATCH($A14,'Fee Switch-Off'!$A$5:$A$30,0)) -> 1200 | G14: 9.5 | H14: =IF(ISNUMBER(SEARCH("TFI",INDEX('Fee Switch-Off'!$C$5:$C$30,MATCH($A14,'Fee Switch-Off'!$A$5:$A$30,0)))),Assumptions!$B$8,Assumptions!$B$7) -> 0.85 | I14: =INDEX('Quote Summary'!$E$5:$E$30,MATCH($A14,'Quote Summary'!$A$5:$A$30,0)) -> 0 | J14: =Assumptions!$B$9 -> 0.35 | K14: =Assumptions!$B$10 -> 1.725 | L14: =Assumptions!$B$11 -> 0 | M14: =(G14-(H14+J14+I14+L14))/100 -> 0.083 | N14: =F14*(1-(K14)/100)*(((1+M14)^(E14/12)-1)/((1+M14)^(1/12)-1))*(1+M14)^(1/12) -> 87229.039 | O14: =(1+RATE(E14,-F14,0,N14,1))^12-1 -> 0.076044538 | P14: =(G14/100-O14)*100 -> 1.8955462 | Q14: =(G14-(H14))/100 -> 0.0865 | R14: =F14*(1-(0)/100)*(((1+Q14)^(E14/12)-1)/((1+Q14)^(1/12)-1))*(1+Q14)^(1/12) -> 89539.852 | S14: =(1+RATE(E14,-F14,0,R14,1))^12-1 -> 0.0865 | T14: =(G14/100-S14)*100 -> 0.85 | U14: =(G14-(I14))/100 -> 0.095 | V14: =F14*(1-(0)/100)*(((1+U14)^(E14/12)-1)/((1+U14)^(1/12)-1))*(1+U14)^(1/12) -> 91459.471 | W14: =(1+RATE(E14,-F14,0,V14,1))^12-1 -> 0.095 | X14: =(G14/100-W14)*100 -> 9.15934e-14 | Y14: =(G14-(J14))/100 -> 0.0915 | Z14: =F14*(1-(K14)/100)*(((1+Y14)^(E14/12)-1)/((1+Y14)^(1/12)-1))*(1+Y14)^(1/12) -> 89100.581 | AA14: =(1+RATE(E14,-F14,0,Z14,1))^12-1 -> 0.084531592 | AB14: =(G14/100-AA14)*100 -> 1.0468408 | AC14: =T14+X14+AB14 -> 1.8968408 | AD14: =IF(AC14=0,0,ROUND(T14*P14/AC14+1E-9,2)) -> 0.85 | AE14: =IF(AC14=0,0,ROUND(X14*P14/AC14+1E-9,2)) -> 0 | AF14: =IF(AC14=0,0,ROUND(AB14*P14/AC14+1E-9,2)) -> 1.05 | AG14: 0 | AH14: =ROUND(AD14+AE14+AF14+AG14+1E-9,2) -> 1.9
A15: 112333103001 | B15: 3 | C15: =IF(ROUND(D15/12,0)>10,CHOOSE(B15,1,5,10,ROUND(D15/12,0)),CHOOSE(B15,1,3,5,ROUND(D15/12,0))) -> 10 | D15: 180 | E15: =C15*12 -> 120 | F15: =INDEX('Fee Switch-Off'!$F$5:$F$30,MATCH($A15,'Fee Switch-Off'!$A$5:$A$30,0)) -> 1200 | G15: 9.5 | H15: =IF(ISNUMBER(SEARCH("TFI",INDEX('Fee Switch-Off'!$C$5:$C$30,MATCH($A15,'Fee Switch-Off'!$A$5:$A$30,0)))),Assumptions!$B$8,Assumptions!$B$7) -> 0.85 | I15: =INDEX('Quote Summary'!$E$5:$E$30,MATCH($A15,'Quote Summary'!$A$5:$A$30,0)) -> 0 | J15: =Assumptions!$B$9 -> 0.35 | K15: =Assumptions!$B$10 -> 1.725 | L15: =Assumptions!$B$11 -> 0 | M15: =(G15-(H15+J15+I15+L15))/100 -> 0.083 | N15: =F15*(1-(K15)/100)*(((1+M15)^(E15/12)-1)/((1+M15)^(1/12)-1))*(1+M15)^(1/12) -> 217187.14 | O15: =(1+RATE(E15,-F15,0,N15,1))^12-1 -> 0.079691281 | P15: =(G15/100-O15)*100 -> 1.5308719 | Q15: =(G15-(H15))/100 -> 0.0865 | R15: =F15*(1-(0)/100)*(((1+Q15)^(E15/12)-1)/((1+Q15)^(1/12)-1))*(1+Q15)^(1/12) -> 225110.3 | S15: =(1+RATE(E15,-F15,0,R15,1))^12-1 -> 0.0865 | T15: =(G15/100-S15)*100 -> 0.85 | U15: =(G15-(I15))/100 -> 0.095 | V15: =F15*(1-(0)/100)*(((1+U15)^(E15/12)-1)/((1+U15)^(1/12)-1))*(1+U15)^(1/12) -> 235438.51 | W15: =(1+RATE(E15,-F15,0,V15,1))^12-1 -> 0.095 | X15: =(G15/100-W15)*100 -> 9.15934e-14 | Y15: =(G15-(J15))/100 -> 0.0915 | Z15: =F15*(1-(K15)/100)*(((1+Y15)^(E15/12)-1)/((1+Y15)^(1/12)-1))*(1+Y15)^(1/12) -> 227138.77 | AA15: =(1+RATE(E15,-F15,0,Z15,1))^12-1 -> 0.088201875 | AB15: =(G15/100-AA15)*100 -> 0.67981251 | AC15: =T15+X15+AB15 -> 1.5298125 | AD15: =IF(AC15=0,0,ROUND(T15*P15/AC15+1E-9,2)) -> 0.85 | AE15: =IF(AC15=0,0,ROUND(X15*P15/AC15+1E-9,2)) -> 0 | AF15: =IF(AC15=0,0,ROUND(AB15*P15/AC15+1E-9,2)) -> 0.68 | AG15: 0 | AH15: =ROUND(AD15+AE15+AF15+AG15+1E-9,2) -> 1.53
A16: 112333103001 | B16: 4 | C16: =IF(ROUND(D16/12,0)>10,CHOOSE(B16,1,5,10,ROUND(D16/12,0)),CHOOSE(B16,1,3,5,ROUND(D16/12,0))) -> 15 | D16: 180 | E16: =C16*12 -> 180 | F16: =INDEX('Fee Switch-Off'!$F$5:$F$30,MATCH($A16,'Fee Switch-Off'!$A$5:$A$30,0)) -> 1200 | G16: 9.5 | H16: =IF(ISNUMBER(SEARCH("TFI",INDEX('Fee Switch-Off'!$C$5:$C$30,MATCH($A16,'Fee Switch-Off'!$A$5:$A$30,0)))),Assumptions!$B$8,Assumptions!$B$7) -> 0.85 | I16: =INDEX('Quote Summary'!$E$5:$E$30,MATCH($A16,'Quote Summary'!$A$5:$A$30,0)) -> 0 | J16: =Assumptions!$B$9 -> 0.35 | K16: =Assumptions!$B$10 -> 1.725 | L16: =Assumptions!$B$11 -> 0 | M16: =(G16-(H16+J16+I16+L16))/100 -> 0.083 | N16: =F16*(1-(K16)/100)*(((1+M16)^(E16/12)-1)/((1+M16)^(1/12)-1))*(1+M16)^(1/12) -> 410805.11 | O16: =(1+RATE(E16,-F16,0,N16,1))^12-1 -> 0.080904727 | P16: =(G16/100-O16)*100 -> 1.4095273 | Q16: =(G16-(H16))/100 -> 0.0865 | R16: =F16*(1-(0)/100)*(((1+Q16)^(E16/12)-1)/((1+Q16)^(1/12)-1))*(1+Q16)^(1/12) -> 430374.72 | S16: =(1+RATE(E16,-F16,0,R16,1))^12-1 -> 0.0865 | T16: =(G16/100-S16)*100 -> 0.85 | U16: =(G16-(I16))/100 -> 0.095 | V16: =F16*(1-(0)/100)*(((1+U16)^(E16/12)-1)/((1+U16)^(1/12)-1))*(1+U16)^(1/12) -> 462095.9 | W16: =(1+RATE(E16,-F16,0,V16,1))^12-1 -> 0.095 | X16: =(G16/100-W16)*100 -> 9.15934e-14 | Y16: =(G16-(J16))/100 -> 0.0915 | Z16: =F16*(1-(K16)/100)*(((1+Y16)^(E16/12)-1)/((1+Y16)^(1/12)-1))*(1+Y16)^(1/12) -> 440993.04 | AA16: =(1+RATE(E16,-F16,0,Z16,1))^12-1 -> 0.089419785 | AB16: =(G16/100-AA16)*100 -> 0.5580215 | AC16: =T16+X16+AB16 -> 1.4080215 | AD16: =IF(AC16=0,0,ROUND(T16*P16/AC16+1E-9,2)) -> 0.85 | AE16: =IF(AC16=0,0,ROUND(X16*P16/AC16+1E-9,2)) -> 0 | AF16: =IF(AC16=0,0,ROUND(AB16*P16/AC16+1E-9,2)) -> 0.56 | AG16: 0 | AH16: =ROUND(AD16+AE16+AF16+AG16+1E-9,2) -> 1.41
... A108: 114723506001 | B108: 4 | C108: =IF(ROUND(D108/12,0)>10,CHOOSE(B108,1,5,10,ROUND(D108/12,0)),CHOOSE(B108,1,3,5,ROUND(D108/12,0))) -> 20 | D108: 240 | E108: =C108*12 -> 240 | F108: =INDEX('Fee Switch-Off'!$F$5:$F$30,MATCH($A108,'Fee Switch-Off'!$A$5:$A$30,0)) -> 2400 | G108: 9.05 | H108: =IF(ISNUMBER(SEARCH("TFI",INDEX('Fee Switch-Off'!$C$5:$C$30,MATCH($A108,'Fee Switch-Off'!$A$5:$A$30,0)))),Assumptions!$B$8,Assumptions!$B$7) -> 0.85 | I108: =INDEX('Quote Summary'!$E$5:$E$30,MATCH($A108,'Quote Summary'!$A$5:$A$30,0)) -> 0 | J108: =Assumptions!$B$9 -> 0.35 | K108: =Assumptions!$B$10 -> 1.725 | L108: =Assumptions!$B$11 -> 0 | M108: =(G108-(H108+J108+I108+L108))/100 -> 0.0785 | N108: =F108*(1-(K108)/100)*(((1+M108)^(E108/12)-1)/((1+M108)^(1/12)-1))*(1+M108)^(1/12) -> 1327430.8 | O108: =(1+RATE(E108,-F108,0,N108,1))^12-1 -> 0.076993562 | P108: =(G108/100-O108)*100 -> 1.3506438 | Q108: =(G108-(H108))/100 -> 0.082 | R108: =F108*(1-(0)/100)*(((1+Q108)^(E108/12)-1)/((1+Q108)^(1/12)-1))*(1+Q108)^(1/12) -> 1406639.8 | S108: =(1+RATE(E108,-F108,0,R108,1))^12-1 -> 0.082 | T108: =(G108/100-S108)*100 -> 0.85 | U108: =(G108-(I108))/100 -> 0.0905 | V108: =F108*(1-(0)/100)*(((1+U108)^(E108/12)-1)/((1+U108)^(1/12)-1))*(1+U108)^(1/12) -> 1553378.1 | W108: =(1+RATE(E108,-F108,0,V108,1))^12-1 -> 0.0905 | X108: =(G108/100-W108)*100 -> 4.2049697e-13 | Y108: =(G108-(J108))/100 -> 0.087 | Z108: =F108*(1-(K108)/100)*(((1+Y108)^(E108/12)-1)/((1+Y108)^(1/12)-1))*(1+Y108)^(1/12) -> 1465285.9 | AA108: =(1+RATE(E108,-F108,0,Z108,1))^12-1 -> 0.085509506 | AB108: =(G108/100-AA108)*100 -> 0.49904943 | AC108: =T108+X108+AB108 -> 1.3490494 | AD108: =IF(AC108=0,0,ROUND(T108*P108/AC108+1E-9,2)) -> 0.85 | AE108: =IF(AC108=0,0,ROUND(X108*P108/AC108+1E-9,2)) -> 0 | AF108: =IF(AC108=0,0,ROUND(AB108*P108/AC108+1E-9,2)) -> 0.5 | AG108: 0 | AH108: =ROUND(AD108+AE108+AF108+AG108+1E-9,2) -> 1.35
